Workbook

Sheet pipeline_collection
B1: Commodity
A2: Conversion rate | C2: €/$ | D2: 0.88
A3: Energy denstiy | B3: H2 | C3: MWh/t | D3: 33.33 | E3: MWh/m³ | F3: 1.4 | G3: 700 bar | H3: https://www.wasserstoff-leitprojekte.de/lw_resource/datapool/systemfiles/elements/files/F4941D1CBA383928E0537E695E862E63/live/document/Wasserstoff-Verfl%C3%BCssigung,_Speicherung,_Transport_und_Anwendung_von_fl%C3%BCssigem_Wasserstoff__2_.pdf | S3: Volumenstromrechnung Wasserstoffpipeline | T3: Q_H2 [Nm³/h] = 3.7435·10⁻³ · (Tn/pn) · [(p1² - p2²)/(G_H2 · L · T · Z)]^0.5 · D^2.667
A4: Energy denstiy | B4: H2 | C4: MWh/t | D4: 33.33 | E4: MWh/m³ | F4: 2.3 | G4: ="-253°C" -> -253°C
A5: Energy denstiy | B5: NH3 | C5: MWh/t | D5: 5.2 | E5: MWh/m³ | F5: 3.6 | H5: https://www.wasserstoff-leitprojekte.de/lw_resource/datapool/systemfiles/elements/files/F4941D1CBA383928E0537E695E862E63/live/document/Wasserstoff-Verfl%C3%BCssigung,_Speicherung,_Transport_und_Anwendung_von_fl%C3%BCssigem_Wasserstoff__2_.pdf | S5: Literature Value
A6: Energy denstiy | B6: MeOH | C6: MWh/t | D6: 5.5 | E6: MWh/m³ | F6: 4.4 | S6: Calculated Value
A7: Energy denstiy | B7: SNG | C7: MWh/t | D7: 13.9 | E7: MWh/m³ | F7: 6.6 | S7: Expert assumption
A8: Energy denstiy | B8: Diesel | C8: MWh/t | D8: 11.9 | E8: MWh/m³ | F8: 9.8 | H8: https://www.wasserstoff-leitprojekte.de/lw_resource/datapool/systemfiles/elements/files/F4941D1CBA383928E0537E695E862E63/live/document/Wasserstoff-Verfl%C3%BCssigung,_Speicherung,_Transport_und_Anwendung_von_fl%C3%BCssigem_Wasserstoff__2_.pdf | S8: AI value
A10: Invest Cost | B10: €/MW/km | C10: 267 | F10: Welder et al https://doi.org/10.1016/j.energy.2018.05.059, PyPSA | S10: G_h2 | T10: - | U10: 0.0696
A11: Invest cost for rated capacity 6 GW | B11: €/km | C11: 1600000 | F11: Welder et al https://doi.org/10.1016/j.energy.2018.05.059
A12: fom | B12: €/km/a | C12: =5*1000 -> 5000 | F12: Welder et al https://doi.org/10.1016/j.energy.2018.05.059
A13: Investment cost fee for transported energy | B13: €/MWh/km | C13: =(C11*C25+C12)/(18000*C22) -> 0.001183454 | F13: Welder et al https://doi.org/10.1016/j.energy.2018.05.059
A14: Invest cost for rated capacity | B14: €/km | C14: =C10*E23 -> 3471000 | S14: Tn
A15: Diameter | B15: m | C15: =T41/1000 -> 0.99
A16: Pipeline invest cost per diameter | B16: $/m | C16: =3200*C15^2+478.9*C15+263.2 -> 3873.631 | D16: €/km | E16: =C16*D2*1000 -> 3408795.3 | F16: IEA, 2019, Belfer-Center Report
A17: Lifetime | B17: a | C17: 50 | F17: Leenings, 2024; Flamme, 2021 | S17: pn
A18: Lifetime | B18: a | C18: 40 | F18: Welder et al https://doi.org/10.1016/j.energy.2018.05.059
A19: WACC | B19: - | C19: 0.06 | S19: deltap
A20: Cost share piping | B20: - | C20: 0.6 | F20: https://ehb.eu/files/downloads/2020_European-Hydrogen-Backbone_Report.pdf | S20: L
A21: Cast share compressors | B21: - | C21: 0.4 | F21: https://ehb.eu/files/downloads/2020_European-Hydrogen-Backbone_Report.pdf | S21: T
A22: Load factor | B22: h/a | C22: 5000 | D22: - | E22: =C22/8760 -> 0.57077626 | F22: https://ehb.eu/files/downloads/2020_European-Hydrogen-Backbone_Report.pdf | S22: Z
A23: Capacity of hydrogen flow (at full load factor) | B23: GW | C23: 13 | D23: MW | E23: =C23*1000 -> 13000 | F23: https://ehb.eu/files/downloads/2020_European-Hydrogen-Backbone_Report.pdf | S23: D
A24: Pipeline diameter | B24: " | C24: 48 | D24: cm | E24: =C24*2.54 -> 121.92 | F24: https://ehb.eu/files/downloads/2020_European-Hydrogen-Backbone_Report.pdf
A25: Annuity factor | B25: a | C25: =((1+C19)^C17*C19)/((1+C19)^C17-1) -> 0.063444286 | T25: Inner diameter | U25: Specific capital costs | V25: °Q_h2 | W25: P_transport | X25: Look up table capacity
A26: Annuity | B26: €/km/a | C26: =C25*C14 -> 220215.12 | T26: mm | U26: €/km | V26: Nm³/h | W26: MW | X26: GW min | Y26: GW mean | Z26: GW max
A27: Transported energy amount | B27: MWh | C27: =E23*C22 -> 65000000 | S27: DN100 | W27: =V27*10.8/3600 -> 0
A28: Investment cost fee for transported energy | B28: €/MWh/km/a | C28: =C26/C27 -> 0.0033879249 | S28: DN125 | W28: =V28*10.8/3600 -> 0
C29: Low | D29: Medium | E29: High | F29: Source | S29: DN150 | W29: =V29*10.8/3600 -> 0
A30: OPEX excluding electricity | B30: €/km/a | C30: =0.7*10^9/22900 -> 30567.686 | D30: =0.9*10^9/22900 -> 39301.31 | E30: =1.1*10^9/22900 -> 48034.934 | F30: https://ehb.eu/files/downloads/2020_European-Hydrogen-Backbone_Report.pdf | Q30: Verteilende Fernleitungen | S30: DN200 | W30: =V30*10.8/3600 -> 0
A31: Electricity demand as share of transported hydrogen energy at 57% load share for every 1000km electric compression | B31: 1/1000km | C31: 0.015 | D31: =(E31-C31)/2+C31 -> 0.019 | E31: 0.023 | F31: https://ehb.eu/files/downloads/2020_European-Hydrogen-Backbone_Report.pdf | S31: DN250 | W31: =V31*10.8/3600 -> 0
A32: Electricity demand as share of transported hydrogen energy at 57% load share for every km electric compression | B32: 1/km | C32: =C31/1000 -> 1.5e-05 | D32: =D31/1000 -> 1.9e-05 | E32: =E31/1000 -> 2.3e-05 | F32: https://ehb.eu/files/downloads/2020_European-Hydrogen-Backbone_Report.pdf | R32: Wasserstoff Fernleitungen | S32: DN300 | T32: 300 | W32: =V32*10.8/3600 -> 0 | X32: 1 | Z32: 1.3
A33: Distance between compressors | B33: km | C33: 100-600 | F33: https://ehb.eu/files/downloads/2020_European-Hydrogen-Backbone_Report.pdf | S33: DN350 | W33: =V33*10.8/3600 -> 0
A34: OPEX electricity costs | B34: €/km/a | C34: =0.9*10^9/22900 -> 39301.31 | D34: =1.2*10^9/22900 -> 52401.747 | E34: =2.4*10^9/22900 -> 104803.49 | F34: https://ehb.eu/files/downloads/2020_European-Hydrogen-Backbone_Report.pdf | P34: Hauptleitungen | S34: DN400 | T34: 400 | W34: =V34*10.8/3600 -> 0 | X34: 2 | Z34: 2.5
A35: TOTAL OPEX | B35: €/km/a | C35: =C34+C30 -> 69868.996 | D35: =D34+D30 -> 91703.057 | E35: =E34+E30 -> 152838.43 | F35: https://ehb.eu/files/downloads/2020_European-Hydrogen-Backbone_Report.pdf | S35: DN450 | W35: =V35*10.8/3600 -> 0
A36: Fom | B36: CAPEX/a | C36: =0.03 -> 0.03 | F36: PyPSA | S36: DN500 | T36: 500 | W36: =V36*10.8/3600 -> 0 | X36: 3.5 | Z36: 4
S37: DN600 | T37: 590 | W37: =V37*10.8/3600 -> 0 | X37: 5.5 | Z37: 6.5
A38: Exemplary assumptions | S38: DN700 | T38: 690 | W38: =V38*10.8/3600 -> 0 | X38: 8 | Z38: 9
A39: H2 | B39: pipeline | C39: 2021 | E39: €/MWhLHV | F39: 36 | G39: €/MWh | H39: =F39 -> 36 | I39: Hampp et al. | K39: Global import to germany | S39: DN800 | T39: 790 | W39: =V39*10.8/3600 -> 0 | X39: 11 | Z39: 13
A40: H2 | B40: pipeline | C40: 2021 | E40: €/MWhLHV | F40: 42 | G40: €/MWh | H40: =F40 -> 42 | I40: Hampp et al. | K40: Global import to germany | S40: DN900 | W40: =V40*10.8/3600 -> 0
A41: H2 | B41: pipeline | C41: 2022 | E41: $/kgH2 | F41: 0.66 | G41: €/MWh | H41: =F41*33.33 -> 21.9978 | I41: Di Lullo et al. | K41: at 1000km | S41: DN1000 | T41: 990 | W41: =V41*10.8/3600 -> 0 | X41: 18 | Z41: 22
A42: H2 | B42: pipeline | C42: 2020 | E42: €/kg/km | F42: =0.16/1000 -> 0.00016 | G42: €/MWh/km | H42: =F42/$D$3*1000 -> 0.00480048 | J42: https://ehb.eu/files/downloads/2020_European-Hydrogen-Backbone_Report.pdf | K42: New Infrastructure | L42: Low | Q42: Leitungen an Kernpunkten | S42: DN1200 | W42: =V42*10.8/3600 -> 0
A43: H2 | B43: pipeline | C43: 2020 | E43: €/kg/km | F43: =0.2/1000 -> 0.0002 | G43: €/MWh/km | H43: =F43/$D$3*1000 -> 0.0060006001 | J43: https://ehb.eu/files/downloads/2020_European-Hydrogen-Backbone_Report.pdf | K43: New Infrastructure | L43: Medium | S43: DN1400 | U43: =2.7*10^6 -> 2700000 | W43: =V43*10.8/3600 -> 0
A44: H2 | B44: pipeline | C44: 2020 | E44: €/kg/km | F44: =0.23/1000 -> 0.00023 | G44: €/MWh/km | H44: =F44/$D$3*1000 -> 0.0069006901 | J44: https://ehb.eu/files/downloads/2020_European-Hydrogen-Backbone_Report.pdf | K44: New Infrastructure | L44: High | S44: DN1600 | W44: =V44*10.8/3600 -> 0
A45: H2 | B45: pipeline | C45: 2020 | E45: €/kg/km | F45: =0.07/1000 -> 7e-05 | G45: €/MWh/km | H45: =F45/$D$3*1000 -> 0.00210021 | J45: https://ehb.eu/files/downloads/2020_European-Hydrogen-Backbone_Report.pdf | K45: Retrofit | L45: Low
A46: H2 | B46: pipeline | C46: 2020 | E46: €/kg/km | F46: =0.11/1000 -> 0.00011 | G46: €/MWh/km | H46: =F46/$D$3*1000 -> 0.00330033 | J46: https://ehb.eu/files/downloads/2020_European-Hydrogen-Backbone_Report.pdf | K46: Retrofit | L46: Medium
A47: H2 | B47: pipeline | C47: 2020 | E47: €/kg/km | F47: =0.15/1000 -> 0.00015 | G47: €/MWh/km | H47: =F47/$D$3*1000 -> 0.00450045 | J47: https://ehb.eu/files/downloads/2020_European-Hydrogen-Backbone_Report.pdf | K47: Retrofit | L47: High
A48: H2 | B48: pipeline | C48: 2020 | E48: €/kg/km | F48: =0.09/1000 -> 9e-05 | G48: €/MWh/km | H48: =F48/$D$3*1000 -> 0.00270027 | J48: https://ehb.eu/files/downloads/2020_European-Hydrogen-Backbone_Report.pdf | K48: Adjusted 75% retrofit EUH2BB | L48: Low
A49: H2 | B49: pipeline | C49: 2020 | E49: €/kg/km | F49: =0.13/1000 -> 0.00013 | G49: €/MWh/km | H49: =F49/$D$3*1000 -> 0.00390039 | J49: https://ehb.eu/files/downloads/2020_European-Hydrogen-Backbone_Report.pdf | K49: Adjusted 75% retrofit EUH2BB | L49: Medium
A50: H2 | B50: pipeline | C50: 2020 | E50: €/kg/km | F50: =0.17/1000 -> 0.00017 | G50: €/MWh/km | H50: =F50/$D$3*1000 -> 0.0051005101 | J50: https://ehb.eu/files/downloads/2020_European-Hydrogen-Backbone_Report.pdf | K50: Adjusted 75% retrofit EUH2BB | L50: High
A52: What | B52: Formula | C52: Unit | D52: Hydrogen | E52: Hgas
A53: energy transport capacity | B53: ="°E ~ C*(Ws/sqrt(K))" -> °E ~ C*(Ws/sqrt(K)) | C53: MW | J53: https://www.wasserstoff-leitprojekte.de/lw_resource/datapool/systemfiles/elements/files/573e9b52-55a3-11f0-84bf-fa163ed847d2/live/document/Compression_and_hydrogen_transport-_A_technical_and_economic_analysis.pdf
A54: energy transport capacity | B54: ="Qn*Hs" -> Qn*Hs | C54: MW
A55: Wobbe Number Ws | B55: ="Hsn/sqrt(dn)" -> Hsn/sqrt(dn) | D55: 13.4 | E55: 14.7
A56: Gas law deviation coefficient K | B56: ="Z/Zn" -> Z/Zn | D56: 1.03 | E56: 0.87
A64: Transport efficiency
A65: pipeline_loss_fixMin | B65: - | C65: 0.005
A66: pipeline_loss_log | B66: (log base) | C66: 100
A67: length mean | C67: 1000
A69: length (km) | C69: Losses | D69: Efficiency
A70: 10 | C70: =1/100*($C$65+(LOG(A70,$C$66)*(A70/$C$67))) -> 0.0001 | D70: =1-C70 -> 0.9999
A71: 50 | C71: =1/100*($C$65+(LOG(A71,$C$66)*(A71/$C$67))) -> 0.0004747425 | D71: =1-C71 -> 0.99952526
A72: 100 | C72: =1/100*($C$65+(LOG(A72,$C$66)*(A72/$C$67))) -> 0.00105 | D72: =1-C72 -> 0.99895
A73: 200 | C73: =1/100*($C$65+(LOG(A73,$C$66)*(A73/$C$67))) -> 0.00235103 | D73: =1-C73 -> 0.99764897
A74: 300 | C74: =1/100*($C$65+(LOG(A74,$C$66)*(A74/$C$67))) -> 0.0037656819 | D74: =1-C74 -> 0.99623432
A75: 400 | C75: =1/100*($C$65+(LOG(A75,$C$66)*(A75/$C$67))) -> 0.00525412 | D75: =1-C75 -> 0.99474588
A76: 500 | C76: =1/100*($C$65+(LOG(A76,$C$66)*(A76/$C$67))) -> 0.006797425 | D76: =1-C76 -> 0.99320257
A77: 600 | C77: =1/100*($C$65+(LOG(A77,$C$66)*(A77/$C$67))) -> 0.0083844538 | D77: =1-C77 -> 0.99161555
A78: 700 | C78: =1/100*($C$65+(LOG(A78,$C$66)*(A78/$C$67))) -> 0.010007843 | D78: =1-C78 -> 0.98999216
A79: 800 | C79: =1/100*($C$65+(LOG(A79,$C$66)*(A79/$C$67))) -> 0.01166236 | D79: =1-C79 -> 0.98833764
A80: 900 | C80: =1/100*($C$65+(LOG(A80,$C$66)*(A80/$C$67))) -> 0.013344091 | D80: =1-C80 -> 0.98665591
A81: 1000 | C81: =1/100*($C$65+(LOG(A81,$C$66)*(A81/$C$67))) -> 0.01505 | D81: =1-C81 -> 0.98495
... A91: 2000 | C91: =1/100*($C$65+(LOG(A91,$C$66)*(A91/$C$67))) -> 0.0330603 | D91: =1-C91 -> 0.9669397

Sheet pipeline_data
A1: name | B1: lon | C1: lat | D1: alternative | E1: commodity | F1: invest_cost_MWh | G1: lifetime | H1: WACC | I1: annuity_factor | J1: invest_cost | K1: DN | L1: capacity | M1: full_load_hours | N1: fom_cost_MWh | O1: regional_factor | P1: fom_capex_factor | Q1: vom_cost_MWh | R1: electricity_per_energy_transported | S1: cost_el | T1: total_cost_MWh
A2: AF-AGO | B2: 17.873887 | C2: -11.202692 | D2: Base | E2: h2 | F2: =(J2*I2)/(L2*M2) -> 0.0021213368 | G2: 40 | H2: 0.11794509 | I2: =((1+H2)^G2*H2)/((1+H2)^G2-1) -> 0.1193252 | J2: 1600000 | K2: 1000 | L2: 18000 | M2: 5000 | N2: =P2*F2*0.5*(1+O2) -> 3.5002058e-05 | O2: 0.1 | P2: 0.03 | Q2: =R2*S2 -> 0.0014444028 | R2: =0.019/1000 -> 1.9e-05 | S2: 76.0212 | T2: =F2+Q2+N2 -> 0.0036007417
A3: AF-BDI | B3: 29.918886 | C3: -3.373056 | D3: Base | E3: h2 | F3: =(J3*I3)/(L3*M3) -> 0.0040118804 | G3: 40 | H3: 0.22560228 | I3: =((1+H3)^G3*H3)/((1+H3)^G3-1) -> 0.22566827 | J3: 1600000 | K3: 1000 | L3: 18000 | M3: 5000 | N3: =P3*F3*0.5*(1+O3) -> 6.6196026e-05 | O3: 0.1 | P3: 0.03 | Q3: =R3*S3 -> 0.0015354261 | R3: =0.019/1000 -> 1.9e-05 | S3: 80.8119 | T3: =F3+Q3+N3 -> 0.0056135025
A4: AF-BEN | B4: 2.315834 | C4: 9.30769 | D4: Base | E4: h2 | F4: =(J4*I4)/(L4*M4) -> 0.0017838705 | G4: 40 | H4: 0.097954265 | I4: =((1+H4)^G4*H4)/((1+H4)^G4-1) -> 0.10034271 | J4: 1600000 | K4: 1000 | L4: 18000 | M4: 5000 | N4: =P4*F4*0.5*(1+O4) -> 2.9433863e-05 | O4: 0.1 | P4: 0.03 | Q4: =R4*S4 -> 0.0014811051 | R4: =0.019/1000 -> 1.9e-05 | S4: 77.9529 | T4: =F4+Q4+N4 -> 0.0032944094
A5: AF-BFA | B5: -1.561593 | C5: 12.238333 | D5: Base | E5: h2 | F5: =(J5*I5)/(L5*M5) -> 0.0022505015 | G5: 40 | H5: 0.1254712 | I5: =((1+H5)^G5*H5)/((1+H5)^G5-1) -> 0.12659071 | J5: 1600000 | K5: 1000 | L5: 18000 | M5: 5000 | N5: =P5*F5*0.5*(1+O5) -> 3.7133275e-05 | O5: 0.1 | P5: 0.03 | Q5: =R5*S5 -> 0.0014427916 | R5: =0.019/1000 -> 1.9e-05 | S5: 75.9364 | T5: =F5+Q5+N5 -> 0.0037304264
A6: AF-BWA | B6: 24.684866 | C6: -22.328474 | D6: Base | E6: h2 | F6: =(J6*I6)/(L6*M6) -> 0.0013457921 | G6: 40 | H6: 0.070793106 | I6: =((1+H6)^G6*H6)/((1+H6)^G6-1) -> 0.075700804 | J6: 1600000 | K6: 1000 | L6: 18000 | M6: 5000 | N6: =P6*F6*0.5*(1+O6) -> 2.2205569e-05 | O6: 0.1 | P6: 0.03 | Q6: =R6*S6 -> 0.0008967145 | R6: =0.019/1000 -> 1.9e-05 | S6: 47.1955 | T6: =F6+Q6+N6 -> 0.0022647121
A7: AF-CAF | B7: 20.939444 | C7: 6.611111 | D7: Base | E7: h2 | F7: =(J7*I7)/(L7*M7) -> 0.0040118804 | G7: 40 | H7: 0.22560228 | I7: =((1+H7)^G7*H7)/((1+H7)^G7-1) -> 0.22566827 | J7: 1600000 | K7: 1000 | L7: 18000 | M7: 5000 | N7: =P7*F7*0.5*(1+O7) -> 6.6196026e-05 | O7: 0.1 | P7: 0.03 | Q7: =R7*S7 -> 0.0014456454 | R7: =0.019/1000 -> 1.9e-05 | S7: 76.0866 | T7: =F7+Q7+N7 -> 0.0055237218
A8: AF-CIV | B8: -5.54708 | C8: 7.539989 | D8: Base | E8: h2 | F8: =(J8*I8)/(L8*M8) -> 0.0015937035 | G8: 40 | H8: 0.08638626 | I8: =((1+H8)^G8*H8)/((1+H8)^G8-1) -> 0.089645824 | J8: 1600000 | K8: 1000 | L8: 18000 | M8: 5000 | N8: =P8*F8*0.5*(1+O8) -> 2.6296108e-05 | O8: 0.1 | P8: 0.03 | Q8: =R8*S8 -> 0.0014175368 | R8: =0.019/1000 -> 1.9e-05 | S8: 74.6072 | T8: =F8+Q8+N8 -> 0.0030375365
A9: AF-CMR | B9: 12.354722 | C9: 7.369722 | D9: Base | E9: h2 | F9: =(J9*I9)/(L9*M9) -> 0.0022073246 | G9: 40 | H9: 0.12296142 | I9: =((1+H9)^G9*H9)/((1+H9)^G9-1) -> 0.12416201 | J9: 1600000 | K9: 1000 | L9: 18000 | M9: 5000 | N9: =P9*F9*0.5*(1+O9) -> 3.6420856e-05 | O9: 0.1 | P9: 0.03 | Q9: =R9*S9 -> 0.0015079787 | R9: =0.019/1000 -> 1.9e-05 | S9: 79.3673 | T9: =F9+Q9+N9 -> 0.0037517242
A10: AF-COD | B10: 21.758664 | C10: -4.038333 | D10: Base | E10: h2 | F10: =(J10*I10)/(L10*M10) -> 0.0020817976 | G10: 40 | H10: 0.11562961 | I10: =((1+H10)^G10*H10)/((1+H10)^G10-1) -> 0.11710111 | J10: 1600000 | K10: 1000 | L10: 18000 | M10: 5000 | N10: =P10*F10*0.5*(1+O10) -> 3.434966e-05 | O10: 0.1 | P10: 0.03 | Q10: =R10*S10 -> 0.0014910041 | R10: =0.019/1000 -> 1.9e-05 | S10: 78.4739 | T10: =F10+Q10+N10 -> 0.0036071513
A11: AF-COG | B11: 15.827659 | C11: -0.228021 | D11: Base | E11: h2 | F11: =(J11*I11)/(L11*M11) -> 0.00248294 | G11: 40 | H11: 0.13889675 | I11: =((1+H11)^G11*H11)/((1+H11)^G11-1) -> 0.13966537 | J11: 1600000 | K11: 1000 | L11: 18000 | M11: 5000 | N11: =P11*F11*0.5*(1+O11) -> 4.0968509e-05 | O11: 0.1 | P11: 0.03 | Q11: =R11*S11 -> 0.0014880914 | R11: =0.019/1000 -> 1.9e-05 | S11: 78.3206 | T11: =F11+Q11+N11 -> 0.0040119999
A12: AF-CPV | B12: -24.013197 | C12: 16.002082 | D12: Base | E12: h2 | F12: =(J12*I12)/(L12*M12) -> 0.0040118804 | G12: 40 | H12: =MAX($H$2:$H$11,$H$13:$H$16,$H$18:$H$33,$H$35:$H$52) -> 0.22560228 | I12: =((1+H12)^G12*H12)/((1+H12)^G12-1) -> 0.22566827 | J12: 1600000 | K12: 1000 | L12: 18000 | M12: 5000 | N12: =P12*F12*0.5*(1+O12) -> 6.6196026e-05 | O12: 0.1 | P12: 0.03 | Q12: =R12*S12 -> 0.0016339069 | R12: =0.019/1000 -> 1.9e-05 | S12: 85.9951 | T12: =F12+Q12+N12 -> 0.0057119833
A13: AF-DJI | B13: 42.590275 | C13: 11.825138 | D13: Base | E13: h2 | F13: =(J13*I13)/(L13*M13) -> 0.0040118804 | G13: 40 | H13: 0.22560228 | I13: =((1+H13)^G13*H13)/((1+H13)^G13-1) -> 0.22566827 | J13: 1600000 | K13: 1000 | L13: 18000 | M13: 5000 | N13: =P13*F13*0.5*(1+O13) -> 6.6196026e-05 | O13: 0.1 | P13: 0.03 | Q13: =R13*S13 -> 0.0015735097 | R13: =0.019/1000 -> 1.9e-05 | S13: 82.8163 | T13: =F13+Q13+N13 -> 0.0056515861
A14: AF-DZA | B14: 3.2986825 | C14: 35.271256 | D14: Base | E14: h2 | F14: =(J14*I14)/(L14*M14) -> 0.001588392 | G14: 40 | H14: 0.086058956 | I14: =((1+H14)^G14*H14)/((1+H14)^G14-1) -> 0.08934705 | J14: 1600000 | K14: 1000 | L14: 18000 | M14: 5000 | N14: =P14*F14*0.5*(1+O14) -> 2.6208468e-05 | O14: 0.1 | P14: 0.03 | Q14: =R14*S14 -> 0.0006749389 | R14: =0.019/1000 -> 1.9e-05 | S14: 35.5231 | T14: =F14+Q14+N14 -> 0.0022895394
A15: AF-EGY | B15: 31.216472 | C15: 30.296519 | D15: Base | E15: h2 | F15: =(J15*I15)/(L15*M15) -> 0.0022981056 | G15: 40 | H15: 0.12823197 | I15: =((1+H15)^G15*H15)/((1+H15)^G15-1) -> 0.12926844 | J15: 1600000 | K15: 1000 | L15: 18000 | M15: 5000 | N15: =P15*F15*0.5*(1+O15) -> 3.7918742e-05 | O15: 0.1 | P15: 0.03 | Q15: =R15*S15 -> 0.0006306157 | R15: =0.019/1000 -> 1.9e-05 | S15: 33.1903 | T15: =F15+Q15+N15 -> 0.00296664
A16: AF-ERI | B16: 39.782334 | C16: 15.179384 | D16: Base | E16: h2 | F16: =(J16*I16)/(L16*M16) -> 0.0040118804 | G16: 40 | H16: 0.22560228 | I16: =((1+H16)^G16*H16)/((1+H16)^G16-1) -> 0.22566827 | J16: 1600000 | K16: 1000 | L16: 18000 | M16: 5000 | N16: =P16*F16*0.5*(1+O16) -> 6.6196026e-05 | O16: 0.1 | P16: 0.03 | Q16: =R16*S16 -> 0.0015665975 | R16: =0.019/1000 -> 1.9e-05 | S16: 82.4525 | T16: =F16+Q16+N16 -> 0.0056446739
A17: AF-ESH | B17: -12.885834 | C17: 24.215527 | D17: Base | E17: h2 | F17: =(J17*I17)/(L17*M17) -> 0.0041288829 | G17: 40 | H17: =MAX(H7:H16,H18:H21,H23:H38,H40:H57) -> 0.23219486 | I17: =((1+H17)^G17*H17)/((1+H17)^G17-1) -> 0.23224966 | J17: 1600000 | K17: 1000 | L17: 18000 | M17: 5000 | N17: =P17*F17*0.5*(1+O17) -> 6.8126567e-05 | O17: 0.1 | P17: 0.03 | Q17: =R17*S17 -> 0.0016339069 | R17: =0.019/1000 -> 1.9e-05 | S17: 85.9951 | T17: =F17+Q17+N17 -> 0.0058309163
A18: AF-ETH | B18: 40.489673 | C18: 9.145 | D18: Base | E18: h2 | F18: =(J18*I18)/(L18*M18) -> 0.0024634492 | G18: 40 | H18: 0.13777579 | I18: =((1+H18)^G18*H18)/((1+H18)^G18-1) -> 0.13856902 | J18: 1600000 | K18: 1000 | L18: 18000 | M18: 5000 | N18: =P18*F18*0.5*(1+O18) -> 4.0646912e-05 | O18: 0.1 | P18: 0.03 | Q18: =R18*S18 -> 0.0016339069 | R18: =0.019/1000 -> 1.9e-05 | S18: 85.9951 | T18: =F18+Q18+N18 -> 0.004138003
A19: AF-GAB | B19: 11.609444 | C19: -0.803689 | D19: Base | E19: h2 | F19: =(J19*I19)/(L19*M19) -> 0.0024634492 | G19: 40 | H19: 0.13777579 | I19: =((1+H19)^G19*H19)/((1+H19)^G19-1) -> 0.13856902 | J19: 1600000 | K19: 1000 | L19: 18000 | M19: 5000 | N19: =P19*F19*0.5*(1+O19) -> 4.0646912e-05 | O19: 0.1 | P19: 0.03 | Q19: =R19*S19 -> 0.0015438222 | R19: =0.019/1000 -> 1.9e-05 | S19: 81.2538 | T19: =F19+Q19+N19 -> 0.0040479183
A20: AF-GHA | B20: -1.023194 | C20: 7.946527 | D20: Base | E20: h2 | F20: =(J20*I20)/(L20*M20) -> 0.0026698397 | G20: 40 | H20: 0.14961018 | I20: =((1+H20)^G20*H20)/((1+H20)^G20-1) -> 0.15017848 | J20: 1600000 | K20: 1000 | L20: 18000 | M20: 5000 | N20: =P20*F20*0.5*(1+O20) -> 4.4052355e-05 | O20: 0.1 | P20: 0.03 | Q20: =R20*S20 -> 0.0014871433 | R20: =0.019/1000 -> 1.9e-05 | S20: 78.2707 | T20: =F20+Q20+N20 -> 0.0042010354
A21: AF-GIN | B21: -9.696645 | C21: 9.945587 | D21: Base | E21: h2 | F21: =(J21*I21)/(L21*M21) -> 0.0024940557 | G21: 40 | H21: 0.1395357 | I21: =((1+H21)^G21*H21)/((1+H21)^G21-1) -> 0.14029063 | J21: 1600000 | K21: 1000 | L21: 18000 | M21: 5000 | N21: =P21*F21*0.5*(1+O21) -> 4.1151919e-05 | O21: 0.1 | P21: 0.03 | Q21: =R21*S21 -> 0.0013920806 | R21: =0.019/1000 -> 1.9e-05 | S21: 73.2674 | T21: =F21+Q21+N21 -> 0.0039272882
A22: AF-GMB | B22: -15.310139 | C22: 13.443182 | D22: Base | E22: h2 | F22: =(J22*I22)/(L22*M22) -> 0.0018031123 | G22: 40 | H22: 0.099110374 | I22: =((1+H22)^G22*H22)/((1+H22)^G22-1) -> 0.10142506 | J22: 1600000 | K22: 1000 | L22: 18000 | M22: 5000 | N22: =P22*F22*0.5*(1+O22) -> 2.9751352e-05 | O22: 0.1 | P22: 0.03 | Q22: =R22*S22 -> 0.0013394658 | R22: =0.019/1000 -> 1.9e-05 | S22: 70.4982 | T22: =F22+Q22+N22 -> 0.0031723294
A23: AF-GNB | B23: -15.180413 | C23: 11.803749 | D23: Base | E23: h2 | F23: =(J23*I23)/(L23*M23) -> 0.0021066165 | G23: 40 | H23: 0.11708373 | I23: =((1+H23)^G23*H23)/((1+H23)^G23-1) -> 0.11849718 | J23: 1600000 | K23: 1000 | L23: 18000 | M23: 5000 | N23: =P23*F23*0.5*(1+O23) -> 3.4759172e-05 | O23: 0.1 | P23: 0.03 | Q23: =R23*S23 -> 0.001385176 | R23: =0.019/1000 -> 1.9e-05 | S23: 72.904 | T23: =F23+Q23+N23 -> 0.0035265517
A24: AF-GNQ | B24: 10.267895 | C24: 1.650801 | D24: Base | E24: h2 | F24: =(J24*I24)/(L24*M24) -> 0.0040118804 | G24: 40 | H24: 0.22560228 | I24: =((1+H24)^G24*H24)/((1+H24)^G24-1) -> 0.22566827 | J24: 1600000 | K24: 1000 | L24: 18000 | M24: 5000 | N24: =P24*F24*0.5*(1+O24) -> 6.6196026e-05 | O24: 0.1 | P24: 0.03 | Q24: =R24*S24 -> 0.001536929 | R24: =0.019/1000 -> 1.9e-05 | S24: 80.891 | T24: =F24+Q24+N24 -> 0.0056150054
A25: AF-KEN | B25: 37.906193 | C25: -0.023559 | D25: Base | E25: h2 | F25: =(J25*I25)/(L25*M25) -> 0.0020817976 | G25: 40 | H25: 0.11562961 | I25: =((1+H25)^G25*H25)/((1+H25)^G25-1) -> 0.11710111 | J25: 1600000 | K25: 1000 | L25: 18000 | M25: 5000 | N25: =P25*F25*0.5*(1+O25) -> 3.434966e-05 | O25: 0.1 | P25: 0.03 | Q25: =R25*S25 -> 0.0015755389 | R25: =0.019/1000 -> 1.9e-05 | S25: 82.9231 | T25: =F25+Q25+N25 -> 0.0036916861
A26: AF-LBR | B26: -9.429499 | C26: 6.428055 | D26: Base | E26: h2 | F26: =(J26*I26)/(L26*M26) -> 0.0022603594 | G26: 40 | H26: 0.12604344 | I26: =((1+H26)^G26*H26)/((1+H26)^G26-1) -> 0.12714521 | J26: 1600000 | K26: 1000 | L26: 18000 | M26: 5000 | N26: =P26*F26*0.5*(1+O26) -> 3.729593e-05 | O26: 0.1 | P26: 0.03 | Q26: =R26*S26 -> 0.0014303865 | R26: =0.019/1000 -> 1.9e-05 | S26: 75.2835 | T26: =F26+Q26+N26 -> 0.0037280418
A27: AF-LBY | B27: 16.687794 | C27: 30.664739 | D27: Base | E27: h2 | F27: =(J27*I27)/(L27*M27) -> 0.0013943978 | G27: 40 | H27: 0.073907658 | I27: =((1+H27)^G27*H27)/((1+H27)^G27-1) -> 0.078434879 | J27: 1600000 | K27: 1000 | L27: 18000 | M27: 5000 | N27: =P27*F27*0.5*(1+O27) -> 2.3007564e-05 | O27: 0.1 | P27: 0.03 | Q27: =R27*S27 -> 0.0006530528 | R27: =0.019/1000 -> 1.9e-05 | S27: 34.3712 | T27: =F27+Q27+N27 -> 0.0020704582
A28: AF-LSO | B28: 28.233608 | C28: -29.609988 | D28: Base | E28: h2 | F28: =(J28*I28)/(L28*M28) -> 0.0040118804 | G28: 40 | H28: 0.22560228 | I28: =((1+H28)^G28*H28)/((1+H28)^G28-1) -> 0.22566827 | J28: 1600000 | K28: 1000 | L28: 18000 | M28: 5000 | N28: =P28*F28*0.5*(1+O28) -> 6.6196026e-05 | O28: 0.1 | P28: 0.03 | Q28: =R28*S28 -> 0.0010386426 | R28: =0.019/1000 -> 1.9e-05 | S28: 54.6654 | T28: =F28+Q28+N28 -> 0.005116719
A29: AF-MAR | B29: -6.6901118 | C29: 33.298649 | D29: Base | E29: h2 | F29: =(J29*I29)/(L29*M29) -> 0.0014854775 | G29: 40 | H29: 0.079663627 | I29: =((1+H29)^G29*H29)/((1+H29)^G29-1) -> 0.08355811 | J29: 1600000 | K29: 1000 | L29: 18000 | M29: 5000 | N29: =P29*F29*0.5*(1+O29) -> 2.4510379e-05 | O29: 0.1 | P29: 0.03 | Q29: =R29*S29 -> 0.0007085841 | R29: =0.019/1000 -> 1.9e-05 | S29: 37.2939 | T29: =F29+Q29+N29 -> 0.002218572
... A33: AF-MRT | B33: -10.940835 | C33: 21.00789 | D33: Base | E33: h2 | F33: =(J33*I33)/(L33*M33) -> 0.0040118804 | G33: 40 | H33: 0.22560228 | I33: =((1+H33)^G33*H33)/((1+H33)^G33-1) -> 0.22566827 | J33: 1600000 | K33: 1000 | L33: 18000 | M33: 5000 | N33: =P33*F33*0.5*(1+O33) -> 6.6196026e-05 | O33: 0.1 | P33: 0.03 | Q33: =R33*S33 -> 0.0013446528 | R33: =0.019/1000 -> 1.9e-05 | S33: 70.7712 | T33: =F33+Q33+N33 -> 0.0054227292
A34: AF-MUS | B34: 57.552152 | C34: -20.348404 | D34: Base | E34: h2 | F34: =(J34*I34)/(L34*M34) -> 0.0040118804 | G34: 40 | H34: =MAX($H$2:$H$11,$H$13:$H$16,$H$18:$H$33,$H$35:$H$52) -> 0.22560228 | I34: =((1+H34)^G34*H34)/((1+H34)^G34-1) -> 0.22566827 | J34: 1600000 | K34: 1000 | L34: 18000 | M34: 5000 | N34: =P34*F34*0.5*(1+O34) -> 6.6196026e-05 | O34: 0.1 | P34: 0.03 | Q34: =R34*S34 -> 0.0016339069 | R34: =0.019/1000 -> 1.9e-05 | S34: 85.9951 | T34: =F34+Q34+N34 -> 0.0057119833
A35: AF-MWI | B35: 34.301525 | C35: -13.254308 | D35: Base | E35: h2 | F35: =(J35*I35)/(L35*M35) -> 0.0029273588 | G35: 40 | H35: 0.16428881 | I35: =((1+H35)^G35*H35)/((1+H35)^G35-1) -> 0.16466393 | J35: 1600000 | K35: 1000 | L35: 18000 | M35: 5000 | N35: =P35*F35*0.5*(1+O35) -> 4.830142e-05 | O35: 0.1 | P35: 0.03 | Q35: =R35*S35 -> 0.0011523215 | R35: =0.019/1000 -> 1.9e-05 | S35: 60.6485 | T35: =F35+Q35+N35 -> 0.0041279817
A36: AF-NAM | B36: 18.49041 | C36: -22.95764 | D36: Base | E36: h2 | F36: =(J36*I36)/(L36*M36) -> 0.0017710645 | G36: 40 | H36: 0.097183526 | I36: =((1+H36)^G36*H36)/((1+H36)^G36-1) -> 0.09962238 | J36: 1600000 | K36: 1000 | L36: 18000 | M36: 5000 | N36: =P36*F36*0.5*(1+O36) -> 2.9222565e-05 | O36: 0.1 | P36: 0.03 | Q36: =R36*S36 -> 0.0010683453 | R36: =0.019/1000 -> 1.9e-05 | S36: 56.2287 | T36: =F36+Q36+N36 -> 0.0028686324
A37: AF-NER | B37: 8.081666 | C37: 17.607789 | D37: Base | E37: h2 | F37: =(J37*I37)/(L37*M37) -> 0.0026503445 | G37: 40 | H37: 0.1484954 | I37: =((1+H37)^G37*H37)/((1+H37)^G37-1) -> 0.14908188 | J37: 1600000 | K37: 1000 | L37: 18000 | M37: 5000 | N37: =P37*F37*0.5*(1+O37) -> 4.3730685e-05 | O37: 0.1 | P37: 0.03 | Q37: =R37*S37 -> 0.0010907615 | R37: =0.019/1000 -> 1.9e-05 | S37: 57.4085 | T37: =F37+Q37+N37 -> 0.0037848367
A38: AF-NGA | B38: 8.675277 | C38: 9.081999 | D38: Base | E38: h2 | F38: =(J38*I38)/(L38*M38) -> 0.002233219 | G38: 40 | H38: 0.12446729 | I38: =((1+H38)^G38*H38)/((1+H38)^G38-1) -> 0.12561857 | J38: 1600000 | K38: 1000 | L38: 18000 | M38: 5000 | N38: =P38*F38*0.5*(1+O38) -> 3.6848114e-05 | O38: 0.1 | P38: 0.03 | Q38: =R38*S38 -> 0.0016040332 | R38: =0.019/1000 -> 1.9e-05 | S38: 84.4228 | T38: =F38+Q38+N38 -> 0.0038741003
A39: AF-RWA | B39: 29.873888 | C39: -1.940278 | D39: Base | E39: h2 | F39: =(J39*I39)/(L39*M39) -> 0.0019318924 | G39: 40 | H39: 0.10679194 | I39: =((1+H39)^G39*H39)/((1+H39)^G39-1) -> 0.10866895 | J39: 1600000 | K39: 1000 | L39: 18000 | M39: 5000 | N39: =P39*F39*0.5*(1+O39) -> 3.1876224e-05 | O39: 0.1 | P39: 0.03 | Q39: =R39*S39 -> 0.0015289699 | R39: =0.019/1000 -> 1.9e-05 | S39: 80.4721 | T39: =F39+Q39+N39 -> 0.0034927385
A40: AF-SDN | B40: 30.217636 | C40: 12.862807 | D40: Base | E40: h2 | F40: =(J40*I40)/(L40*M40) -> 0.003877031 | G40: 40 | H40: 0.2180012 | I40: =((1+H40)^G40*H40)/((1+H40)^G40-1) -> 0.21808299 | J40: 1600000 | K40: 1000 | L40: 18000 | M40: 5000 | N40: =P40*F40*0.5*(1+O40) -> 6.3971012e-05 | O40: 0.1 | P40: 0.03 | Q40: =R40*S40 -> 0.0007575015 | R40: =0.019/1000 -> 1.9e-05 | S40: 39.8685 | T40: =F40+Q40+N40 -> 0.0046985035
A41: AF-SEN | B41: -14.452362 | C41: 14.497401 | D41: Base | E41: h2 | F41: =(J41*I41)/(L41*M41) -> 0.0016517703 | G41: 40 | H41: 0.089948372 | I41: =((1+H41)^G41*H41)/((1+H41)^G41-1) -> 0.092912077 | J41: 1600000 | K41: 1000 | L41: 18000 | M41: 5000 | N41: =P41*F41*0.5*(1+O41) -> 2.7254209e-05 | O41: 0.1 | P41: 0.03 | Q41: =R41*S41 -> 0.00134311 | R41: =0.019/1000 -> 1.9e-05 | S41: 70.69 | T41: =F41+Q41+N41 -> 0.0030221345
A42: AF-SLE | B42: -11.779889 | C42: 8.460555 | D42: Base | E42: h2 | F42: =(J42*I42)/(L42*M42) -> 0.002512201 | G42: 40 | H42: 0.14057819 | I42: =((1+H42)^G42*H42)/((1+H42)^G42-1) -> 0.14131131 | J42: 1600000 | K42: 1000 | L42: 18000 | M42: 5000 | N42: =P42*F42*0.5*(1+O42) -> 4.1451317e-05 | O42: 0.1 | P42: 0.03 | Q42: =R42*S42 -> 0.0014047175 | R42: =0.019/1000 -> 1.9e-05 | S42: 73.9325 | T42: =F42+Q42+N42 -> 0.0039583698
A43: AF-SOM | B43: 46.199616 | C43: 5.152149 | D43: Base | E43: h2 | F43: =(J43*I43)/(L43*M43) -> 0.0029647641 | G43: 40 | H43: 0.16641481 | I43: =((1+H43)^G43*H43)/((1+H43)^G43-1) -> 0.16676798 | J43: 1600000 | K43: 1000 | L43: 18000 | M43: 5000 | N43: =P43*F43*0.5*(1+O43) -> 4.8918608e-05 | O43: 0.1 | P43: 0.03 | Q43: =R43*S43 -> 0.0014560669 | R43: =0.019/1000 -> 1.9e-05 | S43: 76.6351 | T43: =F43+Q43+N43 -> 0.0044697496
A44: AF-SWZ | B44: 31.465866 | C44: -26.522503 | D44: Base | E44: h2 | F44: =(J44*I44)/(L44*M44) -> 0.0021015546 | G44: 40 | H44: 0.11678735 | I44: =((1+H44)^G44*H44)/((1+H44)^G44-1) -> 0.11821245 | J44: 1600000 | K44: 1000 | L44: 18000 | M44: 5000 | N44: =P44*F44*0.5*(1+O44) -> 3.4675651e-05 | O44: 0.1 | P44: 0.03 | Q44: =R44*S44 -> 0.0010429233 | R44: =0.019/1000 -> 1.9e-05 | S44: 54.8907 | T44: =F44+Q44+N44 -> 0.0031791536
A45: AF-TCD | B45: 18.732207 | C45: 15.454166 | D45: Base | E45: h2 | F45: =(J45*I45)/(L45*M45) -> 0.0040118804 | G45: 40 | H45: 0.22560228 | I45: =((1+H45)^G45*H45)/((1+H45)^G45-1) -> 0.22566827 | J45: 1600000 | K45: 1000 | L45: 18000 | M45: 5000 | N45: =P45*F45*0.5*(1+O45) -> 6.6196026e-05 | O45: 0.1 | P45: 0.03 | Q45: =R45*S45 -> 0.0013764664 | R45: =0.019/1000 -> 1.9e-05 | S45: 72.4456 | T45: =F45+Q45+N45 -> 0.0054545428
A46: AF-TGO | B46: 0.824782 | C46: 8.619543 | D46: Base | E46: h2 | F46: =(J46*I46)/(L46*M46) -> 0.0021066165 | G46: 40 | H46: 0.11708373 | I46: =((1+H46)^G46*H46)/((1+H46)^G46-1) -> 0.11849718 | J46: 1600000 | K46: 1000 | L46: 18000 | M46: 5000 | N46: =P46*F46*0.5*(1+O46) -> 3.4759172e-05 | O46: 0.1 | P46: 0.03 | Q46: =R46*S46 -> 0.0014956762 | R46: =0.019/1000 -> 1.9e-05 | S46: 78.7198 | T46: =F46+Q46+N46 -> 0.0036370519
... A81: AS-PHL | B81: 121.00812 | C81: 14.616927 | D81: Base | E81: h2 | F81: =(J81*I81)/(L81*M81) -> 0.001433611 | G81: 40 | H81: 0.076397944 | I81: =((1+H81)^G81*H81)/((1+H81)^G81-1) -> 0.080640616 | J81: 1600000 | K81: 1000 | L81: 18000 | M81: 5000 | N81: =P81*F81*0.5*(1+O81) -> 3.4040354e-05 | O81: 0.58296565 | P81: 0.03 | Q81: =R81*S81 -> 0.0012101575 | R81: =0.019/1000 -> 1.9e-05 | S81: 63.6925 | T81: =F81+Q81+N81 -> 0.0026778088
A82: AS-PRK | B82: 127.51009 | C82: 40.339852 | D82: Base | E82: h2 | F82: =(J82*I82)/(L82*M82) -> 0.0041752959 | G82: 40 | H82: =MAX($H$53:$H$81,$H$83:$H$90,$H$92:$H$96) -> 0.23480948 | I82: =((1+H82)^G82*H82)/((1+H82)^G82-1) -> 0.23486039 | J82: 1600000 | K82: 1000 | L82: 18000 | M82: 5000 | N82: =P82*F82*0.5*(1+O82) -> 9.9140249e-05 | O82: 0.58296565 | P82: 0.03 | Q82: =R82*S82 -> 0.0008619711 | R82: =0.019/1000 -> 1.9e-05 | S82: 45.3669 | T82: =F82+Q82+N82 -> 0.0051364072
A83: AS-QAT | B83: 51.183884 | C83: 25.354826 | D83: Base | E83: h2 | F83: =(J83*I83)/(L83*M83) -> 0.0012886555 | G83: 40 | H83: 0.067088829 | I83: =((1+H83)^G83*H83)/((1+H83)^G83-1) -> 0.072486873 | J83: 1600000 | K83: 1000 | L83: 18000 | M83: 5000 | N83: =P83*F83*0.5*(1+O83) -> 3.0598461e-05 | O83: 0.58296565 | P83: 0.03 | Q83: =R83*S83 -> 0.0007928263 | R83: =0.019/1000 -> 1.9e-05 | S83: 41.7277 | T83: =F83+Q83+N83 -> 0.0021120803
A84: AS-RUS | B84: 66.61922 | C84: 57.185329 | D84: Base | E84: h2 | F84: =(J84*I84)/(L84*M84) -> 0.0016203225 | G84: 40 | H84: 0.088022781 | I84: =((1+H84)^G84*H84)/((1+H84)^G84-1) -> 0.09114314 | J84: 1600000 | K84: 1000 | L84: 18000 | M84: 5000 | N84: =P84*F84*0.5*(1+O84) -> 3.8473723e-05 | O84: 0.58296565 | P84: 0.03 | Q84: =R84*S84 -> 0.0006858126 | R84: =0.019/1000 -> 1.9e-05 | S84: 36.0954 | T84: =F84+Q84+N84 -> 0.0023446088
A85: AS-SAU | B85: 45.079162 | C85: 23.885942 | D85: Base | E85: h2 | F85: =(J85*I85)/(L85*M85) -> 0.0012834371 | G85: 40 | H85: 0.066748016 | I85: =((1+H85)^G85*H85)/((1+H85)^G85-1) -> 0.072193336 | J85: 1600000 | K85: 1000 | L85: 18000 | M85: 5000 | N85: =P85*F85*0.5*(1+O85) -> 3.0474552e-05 | O85: 0.58296565 | P85: 0.03 | Q85: =R85*S85 -> 0.0007614649 | R85: =0.019/1000 -> 1.9e-05 | S85: 40.0771 | T85: =F85+Q85+N85 -> 0.0020753765
A86: AS-SGP | B86: 103.81984 | C86: 1.352083 | D86: Base | E86: h2 | F86: =(J86*I86)/(L86*M86) -> 0.0011944596 | G86: 40 | H86: 0.06086611 | I86: =((1+H86)^G86*H86)/((1+H86)^G86-1) -> 0.06718835 | J86: 1600000 | K86: 1000 | L86: 18000 | M86: 5000 | N86: =P86*F86*0.5*(1+O86) -> 2.8361827e-05 | O86: 0.58296565 | P86: 0.03 | Q86: =R86*S86 -> 0.00157073 | R86: =0.019/1000 -> 1.9e-05 | S86: 82.67 | T86: =F86+Q86+N86 -> 0.0027935514
A87: AS-SYR | B87: 38.996815 | C87: 34.802075 | D87: Base | E87: h2 | F87: =(J87*I87)/(L87*M87) -> 0.0039929913 | G87: 40 | H87: 0.22453776 | I87: =((1+H87)^G87*H87)/((1+H87)^G87-1) -> 0.22460576 | J87: 1600000 | K87: 1000 | L87: 18000 | M87: 5000 | N87: =P87*F87*0.5*(1+O87) -> 9.4811521e-05 | O87: 0.58296565 | P87: 0.03 | Q87: =R87*S87 -> 0.0009890545 | R87: =0.019/1000 -> 1.9e-05 | S87: 52.0555 | T87: =F87+Q87+N87 -> 0.0050768573
A88: AS-THA | B88: 100.99254 | C88: 15.870032 | D88: Base | E88: h2 | F88: =(J88*I88)/(L88*M88) -> 0.0014115204 | G88: 40 | H88: 0.074997415 | I88: =((1+H88)^G88*H88)/((1+H88)^G88-1) -> 0.079398025 | J88: 1600000 | K88: 1000 | L88: 18000 | M88: 5000 | N88: =P88*F88*0.5*(1+O88) -> 3.3515826e-05 | O88: 0.58296565 | P88: 0.03 | Q88: =R88*S88 -> 0.0012351216 | R88: =0.019/1000 -> 1.9e-05 | S88: 65.0064 | T88: =F88+Q88+N88 -> 0.0026801579
A89: AS-TJK | B89: 71.276093 | C89: 38.861034 | D89: Base | E89: h2 | F89: =(J89*I89)/(L89*M89) -> 0.0021768551 | G89: 40 | H89: 0.12118675 | I89: =((1+H89)^G89*H89)/((1+H89)^G89-1) -> 0.1224481 | J89: 1600000 | K89: 1000 | L89: 18000 | M89: 5000 | N89: =P89*F89*0.5*(1+O89) -> 5.1688302e-05 | O89: 0.58296565 | P89: 0.03 | Q89: =R89*S89 -> 0.0007501979 | R89: =0.019/1000 -> 1.9e-05 | S89: 39.4841 | T89: =F89+Q89+N89 -> 0.0029787413
A90: AS-TKM | B90: 59.556278 | C90: 38.969719 | D90: Base | E90: h2 | F90: =(J90*I90)/(L90*M90) -> 0.0041288829 | G90: 40 | H90: 0.23219486 | I90: =((1+H90)^G90*H90)/((1+H90)^G90-1) -> 0.23224966 | J90: 1600000 | K90: 1000 | L90: 18000 | M90: 5000 | N90: =P90*F90*0.5*(1+O90) -> 9.8038196e-05 | O90: 0.58296565 | P90: 0.03 | Q90: =R90*S90 -> 0.0007459932 | R90: =0.019/1000 -> 1.9e-05 | S90: 39.2628 | T90: =F90+Q90+N90 -> 0.0049729142
A91: AS-TLS | B91: 125.72754 | C91: -8.874217 | D91: Base | E91: h2 | F91: =(J91*I91)/(L91*M91) -> 0.0041752959 | G91: 40 | H91: =MAX($H$53:$H$81,$H$83:$H$90,$H$92:$H$96) -> 0.23480948 | I91: =((1+H91)^G91*H91)/((1+H91)^G91-1) -> 0.23486039 | J91: 1600000 | K91: 1000 | L91: 18000 | M91: 5000 | N91: =P91*F91*0.5*(1+O91) -> 9.9140249e-05 | O91: 0.58296565 | P91: 0.03 | Q91: =R91*S91 -> 0.0017770263 | R91: =0.019/1000 -> 1.9e-05 | S91: 93.5277 | T91: =F91+Q91+N91 -> 0.0060514624
A92: AS-TUR | B92: 35.243322 | C92: 38.963745 | D92: Base | E92: h2 | F92: =(J92*I92)/(L92*M92) -> 0.0021213368 | G92: 40 | H92: 0.11794509 | I92: =((1+H92)^G92*H92)/((1+H92)^G92-1) -> 0.1193252 | J92: 1600000 | K92: 1000 | L92: 18000 | M92: 5000 | N92: =P92*F92*0.5*(1+O92) -> 5.037005e-05 | O92: 0.58296565 | P92: 0.03 | Q92: =R92*S92 -> 0.0017039276 | R92: =0.019/1000 -> 1.9e-05 | S92: 89.6804 | T92: =F92+Q92+N92 -> 0.0038756345
A93: AS-TWN | B93: 120.96052 | C93: 23.69781 | D93: Base | E93: h2 | F93: =(J93*I93)/(L93*M93) -> 0.001268516 | G93: 40 | H93: 0.065771114 | I93: =((1+H93)^G93*H93)/((1+H93)^G93-1) -> 0.071354024 | J93: 1600000 | K93: 1000 | L93: 18000 | M93: 5000 | N93: =P93*F93*0.5*(1+O93) -> 3.0120259e-05 | O93: 0.58296565 | P93: 0.03 | Q93: =R93*S93 -> 0.0003813452 | R93: =0.019/1000 -> 1.9e-05 | S93: 20.0708 | T93: =F93+Q93+N93 -> 0.0016799814
A94: AS-UZB | B94: 64.585262 | C94: 41.377491 | D94: Base | E94: h2 | F94: =(J94*I94)/(L94*M94) -> 0.0017382051 | G94: 40 | H94: 0.09520084 | I94: =((1+H94)^G94*H94)/((1+H94)^G94-1) -> 0.097774036 | J94: 1600000 | K94: 1000 | L94: 18000 | M94: 5000 | N94: =P94*F94*0.5*(1+O94) -> 4.1272784e-05 | O94: 0.58296565 | P94: 0.03 | Q94: =R94*S94 -> 0.0007378232 | R94: =0.019/1000 -> 1.9e-05 | S94: 38.8328 | T94: =F94+Q94+N94 -> 0.0025173011
A95: AS-VNM | B95: 108.2772 | C95: 14.058324 | D95: Base | E95: h2 | F95: =(J95*I95)/(L95*M95) -> 0.0016203225 | G95: 40 | H95: 0.088022781 | I95: =((1+H95)^G95*H95)/((1+H95)^G95-1) -> 0.09114314 | J95: 1600000 | K95: 1000 | L95: 18000 | M95: 5000 | N95: =P95*F95*0.5*(1+O95) -> 3.8473723e-05 | O95: 0.58296565 | P95: 0.03 | Q95: =R95*S95 -> 0.0011654448 | R95: =0.019/1000 -> 1.9e-05 | S95: 61.3392 | T95: =F95+Q95+N95 -> 0.002824241
A96: AS-YEM | B96: 48.516388 | C96: 15.552727 | D96: Base | E96: h2 | F96: =(J96*I96)/(L96*M96) -> 0.0030489475 | G96: 40 | H96: 0.17119491 | I96: =((1+H96)^G96*H96)/((1+H96)^G96-1) -> 0.1715033 | J96: 1600000 | K96: 1000 | L96: 18000 | M96: 5000 | N96: =P96*F96*0.5*(1+O96) -> 7.2395689e-05 | O96: 0.58296565 | P96: 0.03 | Q96: =R96*S96 -> 0.0008006277 | R96: =0.019/1000 -> 1.9e-05 | S96: 42.1383 | T96: =F96+Q96+N96 -> 0.0039219709
A97: EU-ALB | B97: 20.168331 | C97: 41.153332 | D97: Base | E97: h2 | F97: =(J97*I97)/(L97*M97) -> 0.0018804549 | G97: 40 | H97: 0.10373481 | I97: =((1+H97)^G97*H97)/((1+H97)^G97-1) -> 0.10577559 | J97: 1600000 | K97: 1000 | L97: 18000 | M97: 5000 | N97: =P97*F97*0.5*(1+O97) -> 6.6248576e-05 | O97: 1.348672 | P97: 0.03 | Q97: =R97*S97 -> 0.0010354126 | R97: =0.019/1000 -> 1.9e-05 | S97: 54.4954 | T97: =F97+Q97+N97 -> 0.0029821161
A98: EU-ARM | B98: 45.038189 | C98: 40.069099 | D98: Base | E98: h2 | F98: =(J98*I98)/(L98*M98) -> 0.001720845 | G98: 40 | H98: 0.094150347 | I98: =((1+H98)^G98*H98)/((1+H98)^G98-1) -> 0.096797531 | J98: 1600000 | K98: 1000 | L98: 18000 | M98: 5000 | N98: =P98*F98*0.5*(1+O98) -> 6.0625506e-05 | O98: 1.348672 | P98: 0.03 | Q98: =R98*S98 -> 0.0006165405 | R98: =0.019/1000 -> 1.9e-05 | S98: 32.4495 | T98: =F98+Q98+N98 -> 0.002398011
A99: EU-AUT | B99: 14.550072 | C99: 47.516231 | D99: Base | E99: h2 | F99: =(J99*I99)/(L99*M99) -> 0.001226838 | G99: 40 | H99: 0.063022637 | I99: =((1+H99)^G99*H99)/((1+H99)^G99-1) -> 0.069009637 | J99: 1600000 | K99: 1000 | L99: 18000 | M99: 5000 | N99: =P99*F99*0.5*(1+O99) -> 4.32216e-05 | O99: 1.348672 | P99: 0.03 | Q99: =R99*S99 -> 0.0014089887 | R99: =0.019/1000 -> 1.9e-05 | S99: 74.1573 | T99: =F99+Q99+N99 -> 0.0026790483
A100: EU-AZE | B100: 47.576927 | C100: 40.143105 | D100: Base | E100: h2 | F100: =(J100*I100)/(L100*M100) -> 0.001544679 | G100: 40 | H100: 0.083355359 | I100: =((1+H100)^G100*H100)/((1+H100)^G100-1) -> 0.086888193 | J100: 1600000 | K100: 1000 | L100: 18000 | M100: 5000 | N100: =P100*F100*0.5*(1+O100) -> 5.4419164e-05 | O100: 1.348672 | P100: 0.03 | Q100: =R100*S100 -> 0.0006333023 | R100: =0.019/1000 -> 1.9e-05 | S100: 33.3317 | T100: =F100+Q100+N100 -> 0.0022324005
A101: EU-BEL | B101: 4.469936 | C101: 50.503887 | D101: Base | E101: h2 | F101: =(J101*I101)/(L101*M101) -> 0.001250751 | G101: 40 | H101: 0.064603231 | I101: =((1+H101)^G101*H101)/((1+H101)^G101-1) -> 0.070354745 | J101: 1600000 | K101: 1000 | L101: 18000 | M101: 5000 | N101: =P101*F101*0.5*(1+O101) -> 4.4064058e-05 | O101: 1.348672 | P101: 0.03 | Q101: =R101*S101 -> 0.0015173248 | R101: =0.019/1000 -> 1.9e-05 | S101: 79.8592 | T101: =F101+Q101+N101 -> 0.0028121399
A102: EU-BGR | B102: 25.48583 | C102: 42.733883 | D102: Base | E102: h2 | F102: =(J102*I102)/(L102*M102) -> 0.0014545778 | G102: 40 | H102: 0.077721808 | I102: =((1+H102)^G102*H102)/((1+H102)^G102-1) -> 0.081820003 | J102: 1600000 | K102: 1000 | L102: 18000 | M102: 5000 | N102: =P102*F102*0.5*(1+O102) -> 5.1244893e-05 | O102: 1.348672 | P102: 0.03 | Q102: =R102*S102 -> 0.0010576844 | R102: =0.019/1000 -> 1.9e-05 | S102: 55.6676 | T102: =F102+Q102+N102 -> 0.0025635071
A103: EU-BIH | B103: 17.679076 | C103: 43.915886 | D103: Base | E103: h2 | F103: =(J103*I103)/(L103*M103) -> 0.0022405202 | G103: 40 | H103: 0.12489151 | I103: =((1+H103)^G103*H103)/((1+H103)^G103-1) -> 0.12602926 | J103: 1600000 | K103: 1000 | L103: 18000 | M103: 5000 | N103: =P103*F103*0.5*(1+O103) -> 7.8933704e-05 | O103: 1.348672 | P103: 0.03 | Q103: =R103*S103 -> 0.0010420417 | R103: =0.019/1000 -> 1.9e-05 | S103: 54.8443 | T103: =F103+Q103+N103 -> 0.0033614956
... A105: EU-CHE | B105: 8.227512 | C105: 46.818188 | D105: Base | E105: h2 | F105: =(J105*I105)/(L105*M105) -> 0.0012020099 | G105: 40 | H105: 0.061370732 | I105: =((1+H105)^G105*H105)/((1+H105)^G105-1) -> 0.067613055 | J105: 1600000 | K105: 1000 | L105: 18000 | M105: 5000 | N105: =P105*F105*0.5*(1+O105) -> 4.2346904e-05 | O105: 1.348672 | P105: 0.03 | Q105: =R105*S105 -> 0.0016834057 | R105: =0.019/1000 -> 1.9e-05 | S105: 88.6003 | T105: =F105+Q105+N105 -> 0.0029277625
A106: EU-CYP | B106: 33.429859 | C106: 35.126413 | D106: Base | E106: h2 | F106: =(J106*I106)/(L106*M106) -> 0.0041587192 | G106: 40 | H106: =MAX(H$97:H$105,H$107:H$129,H$131:H$135,H$137:H$156) -> 0.23387569 | I106: =((1+H106)^G106*H106)/((1+H106)^G106-1) -> 0.23392796 | J106: 1600000 | K106: 1000 | L106: 18000 | M106: 5000 | N106: =P106*F106*0.5*(1+O106) -> 0.00014651201 | O106: 1.348672 | P106: 0.03 | Q106: =R106*S106 -> 0.0016998179 | R106: =0.019/1000 -> 1.9e-05 | S106: =MAX(S$97:S$105,S$107:S$129,S$131:S$134,S$137:S$156) -> 89.4641 | T106: =F106+Q106+N106 -> 0.0060050491
A107: EU-CZE | B107: 15.472962 | C107: 49.817492 | D107: Base | E107: h2 | F107: =(J107*I107)/(L107*M107) -> 0.0012720786 | G107: 40 | H107: 0.066004691 | I107: =((1+H107)^G107*H107)/((1+H107)^G107-1) -> 0.07155442 | J107: 1600000 | K107: 1000 | L107: 18000 | M107: 5000 | N107: =P107*F107*0.5*(1+O107) -> 4.481543e-05 | O107: 1.348672 | P107: 0.03 | Q107: =R107*S107 -> 0.0012021338 | R107: =0.019/1000 -> 1.9e-05 | S107: 63.2702 | T107: =F107+Q107+N107 -> 0.0025190278
A108: EU-DEU | B108: 9.234513 | C108: 52.190328 | D108: Base | E108: h2 | F108: =(J108*I108)/(L108*M108) -> 0.0011538477 | G108: 40 | H108: 0.058132743 | I108: =((1+H108)^G108*H108)/((1+H108)^G108-1) -> 0.064903931 | J108: 1600000 | K108: 1000 | L108: 18000 | M108: 5000 | N108: =P108*F108*0.5*(1+O108) -> 4.0650145e-05 | O108: 1.348672 | P108: 0.03 | Q108: =R108*S108 -> 0.0015401685 | R108: =0.019/1000 -> 1.9e-05 | S108: 81.0615 | T108: =F108+Q108+N108 -> 0.0027346663
A109: EU-DNK | B109: 11.753429 | C109: 55.449467 | D109: Base | E109: h2 | F109: =(J109*I109)/(L109*M109) -> 0.001178782 | G109: 40 | H109: 0.059814815 | I109: =((1+H109)^G109*H109)/((1+H109)^G109-1) -> 0.066306487 | J109: 1600000 | K109: 1000 | L109: 18000 | M109: 5000 | N109: =P109*F109*0.5*(1+O109) -> 4.1528584e-05 | O109: 1.348672 | P109: 0.03 | Q109: =R109*S109 -> 0.0012299821 | R109: =0.019/1000 -> 1.9e-05 | S109: 64.7359 | T109: =F109+Q109+N109 -> 0.0024502927
A110: EU-DNK1 | B110: 8.9730721 | C110: 56.12565 | D110: Base | E110: h2 | F110: =(J110*I110)/(L110*M110) -> 0.001178782 | G110: 40 | H110: 0.059814815 | I110: =((1+H110)^G110*H110)/((1+H110)^G110-1) -> 0.066306487 | J110: 1600000 | K110: 1000 | L110: 18000 | M110: 5000 | N110: =P110*F110*0.5*(1+O110) -> 4.1528584e-05 | O110: 1.348672 | P110: 0.03 | Q110: =R110*S110 -> 0.0012299821 | R110: =0.019/1000 -> 1.9e-05 | S110: 64.7359 | T110: =F110+Q110+N110 -> 0.0024502927
A111: EU-DNK2 | B111: 12.314952 | C111: 55.688446 | D111: Base | E111: h2 | F111: =(J111*I111)/(L111*M111) -> 0.001178782 | G111: 40 | H111: 0.059814815 | I111: =((1+H111)^G111*H111)/((1+H111)^G111-1) -> 0.066306487 | J111: 1600000 | K111: 1000 | L111: 18000 | M111: 5000 | N111: =P111*F111*0.5*(1+O111) -> 4.1528584e-05 | O111: 1.348672 | P111: 0.03 | Q111: =R111*S111 -> 0.0012299821 | R111: =0.019/1000 -> 1.9e-05 | S111: 64.7359 | T111: =F111+Q111+N111 -> 0.0024502927
A112: EU-ESP | B112: -3.74922 | C112: 40.463667 | D112: Base | E112: h2 | F112: =(J112*I112)/(L112*M112) -> 0.0013901264 | G112: 40 | H112: 0.073635219 | I112: =((1+H112)^G112*H112)/((1+H112)^G112-1) -> 0.07819461 | J112: 1600000 | K112: 1000 | L112: 18000 | M112: 5000 | N112: =P112*F112*0.5*(1+O112) -> 4.8974264e-05 | O112: 1.348672 | P112: 0.03 | Q112: =R112*S112 -> 0.0012168284 | R112: =0.019/1000 -> 1.9e-05 | S112: 64.0436 | T112: =F112+Q112+N112 -> 0.0026559291
A113: EU-EST | B113: 25.013607 | C113: 58.595272 | D113: Base | E113: h2 | F113: =(J113*I113)/(L113*M113) -> 0.0012834371 | G113: 40 | H113: 0.066748016 | I113: =((1+H113)^G113*H113)/((1+H113)^G113-1) -> 0.072193336 | J113: 1600000 | K113: 1000 | L113: 18000 | M113: 5000 | N113: =P113*F113*0.5*(1+O113) -> 4.5215591e-05 | O113: 1.348672 | P113: 0.03 | Q113: =R113*S113 -> 0.0010707051 | R113: =0.019/1000 -> 1.9e-05 | S113: 56.3529 | T113: =F113+Q113+N113 -> 0.0023993578
A114: EU-FIN | B114: 25.748151 | C114: 61.92411 | D114: Base | E114: h2 | F114: =(J114*I114)/(L114*M114) -> 0.0012404844 | G114: 40 | H114: 0.063925854 | I114: =((1+H114)^G114*H114)/((1+H114)^G114-1) -> 0.069777248 | J114: 1600000 | K114: 1000 | L114: 18000 | M114: 5000 | N114: =P114*F114*0.5*(1+O114) -> 4.3702364e-05 | O114: 1.348672 | P114: 0.03 | Q114: =R114*S114 -> 0.0011118154 | R114: =0.019/1000 -> 1.9e-05 | S114: 58.5166 | T114: =F114+Q114+N114 -> 0.0023960022
A115: EU-FRA | B115: 2.213749 | C115: 46.227638 | D115: Base | E115: h2 | F115: =(J115*I115)/(L115*M115) -> 0.0012362645 | G115: 40 | H115: 0.063646903 | I115: =((1+H115)^G115*H115)/((1+H115)^G115-1) -> 0.06953988 | J115: 1600000 | K115: 1000 | L115: 18000 | M115: 5000 | N115: =P115*F115*0.5*(1+O115) -> 4.3553698e-05 | O115: 1.348672 | P115: 0.03 | Q115: =R115*S115 -> 0.0011388619 | R115: =0.019/1000 -> 1.9e-05 | S115: 59.9401 | T115: =F115+Q115+N115 -> 0.0024186801
A116: EU-GBR | B116: -0.77974118 | C116: 53 | D116: Base | E116: h2 | F116: =(J116*I116)/(L116*M116) -> 0.001250751 | G116: 40 | H116: 0.064603231 | I116: =((1+H116)^G116*H116)/((1+H116)^G116-1) -> 0.070354745 | J116: 1600000 | K116: 1000 | L116: 18000 | M116: 5000 | N116: =P116*F116*0.5*(1+O116) -> 4.4064058e-05 | O116: 1.348672 | P116: 0.03 | Q116: =R116*S116 -> 0.0011797081 | R116: =0.019/1000 -> 1.9e-05 | S116: 62.0899 | T116: =F116+Q116+N116 -> 0.0024745232
A117: EU-GEO | B117: 43.356892 | C117: 42.315407 | D117: Base | E117: h2 | F117: =(J117*I117)/(L117*M117) -> 0.0016470408 | G117: 40 | H117: 0.089659303 | I117: =((1+H117)^G117*H117)/((1+H117)^G117-1) -> 0.092646044 | J117: 1600000 | K117: 1000 | L117: 18000 | M117: 5000 | N117: =P117*F117*0.5*(1+O117) -> 5.8025378e-05 | O117: 1.348672 | P117: 0.03 | Q117: =R117*S117 -> 0.0006168407 | R117: =0.019/1000 -> 1.9e-05 | S117: 32.4653 | T117: =F117+Q117+N117 -> 0.0023219069
A118: EU-GRC | B118: 21.824312 | C118: 39.074208 | D118: Base | E118: h2 | F118: =(J118*I118)/(L118*M118) -> 0.001534772 | G118: 40 | H118: 0.08274007 | I118: =((1+H118)^G118*H118)/((1+H118)^G118-1) -> 0.086330926 | J118: 1600000 | K118: 1000 | L118: 18000 | M118: 5000 | N118: =P118*F118*0.5*(1+O118) -> 5.4070141e-05 | O118: 1.348672 | P118: 0.03 | Q118: =R118*S118 -> 0.0010393722 | R118: =0.019/1000 -> 1.9e-05 | S118: 54.7038 | T118: =F118+Q118+N118 -> 0.0026282144
... A129: EU-ITA6 | B129: 14.249826 | C129: 37.544391 | D129: Base | E129: h2 | F129: =(J129*I129)/(L129*M129) -> 0.001480478 | G129: 40 | H129: 0.079350168 | I129: =((1+H129)^G129*H129)/((1+H129)^G129-1) -> 0.083276888 | J129: 1600000 | K129: 1000 | L129: 18000 | M129: 5000 | N129: =P129*F129*0.5*(1+O129) -> 5.2157358e-05 | O129: 1.348672 | P129: 0.03 | Q129: =R129*S129 -> 0.0016998179 | R129: =0.019/1000 -> 1.9e-05 | S129: 89.4641 | T129: =F129+Q129+N129 -> 0.0032324533
A130: EU-KOS | B130: 20.902977 | C130: 42.602636 | D130: Base | E130: h2 | F130: =(J130*I130)/(L130*M130) -> 0.0041587192 | G130: 40 | H130: =MAX($H$97:$H$105,$H$107:$H$129,$H$131:$H$135,$H$137:$H$156) -> 0.23387569 | I130: =((1+H130)^G130*H130)/((1+H130)^G130-1) -> 0.23392796 | J130: 1600000 | K130: 1000 | L130: 18000 | M130: 5000 | N130: =P130*F130*0.5*(1+O130) -> 0.00014651201 | O130: 1.348672 | P130: 0.03 | Q130: =R130*S130 -> 0.0016998179 | R130: =0.019/1000 -> 1.9e-05 | S130: =MAX(S$97:S$105,S$107:S$129,S$131:S$134,S$137:S$156) -> 89.4641 | T130: =F130+Q130+N130 -> 0.0060050491
A131: EU-LTU | B131: 24.5 | C131: 55.169438 | D131: Base | E131: h2 | F131: =(J131*I131)/(L131*M131) -> 0.0013221529 | G131: 40 | H131: 0.069266443 | I131: =((1+H131)^G131*H131)/((1+H131)^G131-1) -> 0.074371102 | J131: 1600000 | K131: 1000 | L131: 18000 | M131: 5000 | N131: =P131*F131*0.5*(1+O131) -> 4.6579553e-05 | O131: 1.348672 | P131: 0.03 | Q131: =R131*S131 -> 0.0011624656 | R131: =0.019/1000 -> 1.9e-05 | S131: 61.1824 | T131: =F131+Q131+N131 -> 0.0025311981
A132: EU-LUX | B132: 6.129583 | C132: 49.815273 | D132: Base | E132: h2 | F132: =(J132*I132)/(L132*M132) -> 0.001169597 | G132: 40 | H132: 0.059196653 | I132: =((1+H132)^G132*H132)/((1+H132)^G132-1) -> 0.065789831 | J132: 1600000 | K132: 1000 | L132: 18000 | M132: 5000 | N132: =P132*F132*0.5*(1+O132) -> 4.1204995e-05 | O132: 1.348672 | P132: 0.03 | Q132: =R132*S132 -> 0.0015836405 | R132: =0.019/1000 -> 1.9e-05 | S132: 83.3495 | T132: =F132+Q132+N132 -> 0.0027944425
A133: EU-LVA | B133: 24.603189 | C133: 56.879635 | D133: Base | E133: h2 | F133: =(J133*I133)/(L133*M133) -> 0.0013537757 | G133: 40 | H133: 0.071306895 | I133: =((1+H133)^G133*H133)/((1+H133)^G133-1) -> 0.076149881 | J133: 1600000 | K133: 1000 | L133: 18000 | M133: 5000 | N133: =P133*F133*0.5*(1+O133) -> 4.7693624e-05 | O133: 1.348672 | P133: 0.03 | Q133: =R133*S133 -> 0.001155846 | R133: =0.019/1000 -> 1.9e-05 | S133: 60.834 | T133: =F133+Q133+N133 -> 0.0025573153
A134: EU-MDA | B134: 28.369885 | C134: 47.411631 | D134: Base | E134: h2 | F134: =(J134*I134)/(L134*M134) -> 0.0022245834 | G134: 40 | H134: 0.12396532 | I134: =((1+H134)^G134*H134)/((1+H134)^G134-1) -> 0.12513282 | J134: 1600000 | K134: 1000 | L134: 18000 | M134: 5000 | N134: =P134*F134*0.5*(1+O134) -> 7.8372251e-05 | O134: 1.348672 | P134: 0.03 | Q134: =R134*S134 -> 0.001136409 | R134: =0.019/1000 -> 1.9e-05 | S134: 59.811 | T134: =F134+Q134+N134 -> 0.0034393647
A135: EU-MKD | B135: 21.745275 | C135: 41.608635 | D135: Base | E135: h2 | F135: =(J135*I135)/(L135*M135) -> 0.0017672156 | G135: 40 | H135: 0.096951663 | I135: =((1+H135)^G135*H135)/((1+H135)^G135-1) -> 0.099405877 | J135: 1600000 | K135: 1000 | L135: 18000 | M135: 5000 | N135: =P135*F135*0.5*(1+O135) -> 6.2259146e-05 | O135: 1.348672 | P135: 0.03 | Q135: =R135*S135 -> 0.0016998179 | R135: =0.019/1000 -> 1.9e-05 | S135: =MAX(S97:S134,S136:S156) -> 89.4641 | T135: =F135+Q135+N135 -> 0.0035292926
A136: EU-MLT | B136: 14.445882 | C136: 35.88504 | D136: Base | E136: h2 | F136: =(J136*I136)/(L136*M136) -> 0.0041587192 | G136: 40 | H136: =MAX($H$97:$H$105,$H$107:$H$129,$H$131:$H$135,$H$137:$H$156) -> 0.23387569 | I136: =((1+H136)^G136*H136)/((1+H136)^G136-1) -> 0.23392796 | J136: 1600000 | K136: 1000 | L136: 18000 | M136: 5000 | N136: =P136*F136*0.5*(1+O136) -> 0.00014651201 | O136: 1.348672 | P136: 0.03 | Q136: =R136*S136 -> 0.0010501471 | R136: =0.019/1000 -> 1.9e-05 | S136: 55.2709 | T136: =F136+Q136+N136 -> 0.0053553783
A137: EU-MNE | B137: 19.37439 | C137: 42.708678 | D137: Base | E137: h2 | F137: =(J137*I137)/(L137*M137) -> 0.0018804549 | G137: 40 | H137: 0.10373481 | I137: =((1+H137)^G137*H137)/((1+H137)^G137-1) -> 0.10577559 | J137: 1600000 | K137: 1000 | L137: 18000 | M137: 5000 | N137: =P137*F137*0.5*(1+O137) -> 6.6248576e-05 | O137: 1.348672 | P137: 0.03 | Q137: =R137*S137 -> 0.0008392566 | R137: =0.019/1000 -> 1.9e-05 | S137: 44.1714 | T137: =F137+Q137+N137 -> 0.0027859601
A138: EU-NLD | B138: 5.291266 | C138: 52.132633 | D138: Base | E138: h2 | F138: =(J138*I138)/(L138*M138) -> 0.001166915 | G138: 40 | H138: 0.059015831 | I138: =((1+H138)^G138*H138)/((1+H138)^G138-1) -> 0.065638966 | J138: 1600000 | K138: 1000 | L138: 18000 | M138: 5000 | N138: =P138*F138*0.5*(1+O138) -> 4.1110507e-05 | O138: 1.348672 | P138: 0.03 | Q138: =R138*S138 -> 0.0014659146 | R138: =0.019/1000 -> 1.9e-05 | S138: 77.1534 | T138: =F138+Q138+N138 -> 0.0026739401
A139: EU-NOR | B139: 10.672611 | C139: 62.533801 | D139: Base | E139: h2 | F139: =(J139*I139)/(L139*M139) -> 0.001178782 | G139: 40 | H139: 0.059814815 | I139: =((1+H139)^G139*H139)/((1+H139)^G139-1) -> 0.066306487 | J139: 1600000 | K139: 1000 | L139: 18000 | M139: 5000 | N139: =P139*F139*0.5*(1+O139) -> 4.1528584e-05 | O139: 1.348672 | P139: 0.03 | Q139: =R139*S139 -> 0.0011208822 | R139: =0.019/1000 -> 1.9e-05 | S139: 58.9938 | T139: =F139+Q139+N139 -> 0.0023411928
A140: EU-NOR1 | B140: 11.254592 | C140: 60.204071 | D140: Base | E140: h2 | F140: =(J140*I140)/(L140*M140) -> 0.001178782 | G140: 40 | H140: 0.059814815 | I140: =((1+H140)^G140*H140)/((1+H140)^G140-1) -> 0.066306487 | J140: 1600000 | K140: 1000 | L140: 18000 | M140: 5000 | N140: =P140*F140*0.5*(1+O140) -> 4.1528584e-05 | O140: 1.348672 | P140: 0.03 | Q140: =R140*S140 -> 0.0011208822 | R140: =0.019/1000 -> 1.9e-05 | S140: 58.9938 | T140: =F140+Q140+N140 -> 0.0023411928
A141: EU-NOR2 | B141: 7.1577444 | C141: 58.381638 | D141: Base | E141: h2 | F141: =(J141*I141)/(L141*M141) -> 0.001178782 | G141: 40 | H141: 0.059814815 | I141: =((1+H141)^G141*H141)/((1+H141)^G141-1) -> 0.066306487 | J141: 1600000 | K141: 1000 | L141: 18000 | M141: 5000 | N141: =P141*F141*0.5*(1+O141) -> 4.1528584e-05 | O141: 1.348672 | P141: 0.03 | Q141: =R141*S141 -> 0.0011208822 | R141: =0.019/1000 -> 1.9e-05 | S141: 58.9938 | T141: =F141+Q141+N141 -> 0.0023411928
A142: EU-NOR3 | B142: 10.463888 | C142: 64 | D142: Base | E142: h2 | F142: =(J142*I142)/(L142*M142) -> 0.001178782 | G142: 40 | H142: 0.059814815 | I142: =((1+H142)^G142*H142)/((1+H142)^G142-1) -> 0.066306487 | J142: 1600000 | K142: 1000 | L142: 18000 | M142: 5000 | N142: =P142*F142*0.5*(1+O142) -> 4.1528584e-05 | O142: 1.348672 | P142: 0.03 | Q142: =R142*S142 -> 0.0011208822 | R142: =0.019/1000 -> 1.9e-05 | S142: 58.9938 | T142: =F142+Q142+N142 -> 0.0023411928
A143: EU-NOR4 | B143: 17.720099 | C143: 68.8 | D143: Base | E143: h2 | F143: =(J143*I143)/(L143*M143) -> 0.001178782 | G143: 40 | H143: 0.059814815 | I143: =((1+H143)^G143*H143)/((1+H143)^G143-1) -> 0.066306487 | J143: 1600000 | K143: 1000 | L143: 18000 | M143: 5000 | N143: =P143*F143*0.5*(1+O143) -> 4.1528584e-05 | O143: 1.348672 | P143: 0.03 | Q143: =R143*S143 -> 0.0011208822 | R143: =0.019/1000 -> 1.9e-05 | S143: 58.9938 | T143: =F143+Q143+N143 -> 0.0023411928
A144: EU-NOR5 | B144: 6.7667336 | C144: 61.283299 | D144: Base | E144: h2 | F144: =(J144*I144)/(L144*M144) -> 0.001178782 | G144: 40 | H144: 0.059814815 | I144: =((1+H144)^G144*H144)/((1+H144)^G144-1) -> 0.066306487 | J144: 1600000 | K144: 1000 | L144: 18000 | M144: 5000 | N144: =P144*F144*0.5*(1+O144) -> 4.1528584e-05 | O144: 1.348672 | P144: 0.03 | Q144: =R144*S144 -> 0.0011208822 | R144: =0.019/1000 -> 1.9e-05 | S144: 58.9938 | T144: =F144+Q144+N144 -> 0.0023411928
A145: EU-POL | B145: 19.145136 | C145: 51.919438 | D145: Base | E145: h2 | F145: =(J145*I145)/(L145*M145) -> 0.0013071574 | G145: 40 | H145: 0.068293731 | I145: =((1+H145)^G145*H145)/((1+H145)^G145-1) -> 0.073527605 | J145: 1600000 | K145: 1000 | L145: 18000 | M145: 5000 | N145: =P145*F145*0.5*(1+O145) -> 4.605126e-05 | O145: 1.348672 | P145: 0.03 | Q145: =R145*S145 -> 0.0011900289 | R145: =0.019/1000 -> 1.9e-05 | S145: 62.6331 | T145: =F145+Q145+N145 -> 0.0025432376
A146: EU-PRT | B146: -8.224454 | C146: 39.399872 | D146: Base | E146: h2 | F146: =(J146*I146)/(L146*M146) -> 0.0013497821 | G146: 40 | H146: 0.07105 | I146: =((1+H146)^G146*H146)/((1+H146)^G146-1) -> 0.075925245 | J146: 1600000 | K146: 1000 | L146: 18000 | M146: 5000 | N146: =P146*F146*0.5*(1+O146) -> 4.7552932e-05 | O146: 1.348672 | P146: 0.03 | Q146: =R146*S146 -> 0.0011618234 | R146: =0.019/1000 -> 1.9e-05 | S146: 61.1486 | T146: =F146+Q146+N146 -> 0.0025591585
A147: EU-ROU | B147: 24.96676 | C147: 45.943161 | D147: Base | E147: h2 | F147: =(J147*I147)/(L147*M147) -> 0.0015183217 | G147: 40 | H147: 0.081716223 | I147: =((1+H147)^G147*H147)/((1+H147)^G147-1) -> 0.085405597 | J147: 1600000 | K147: 1000 | L147: 18000 | M147: 5000 | N147: =P147*F147*0.5*(1+O147) -> 5.3490595e-05 | O147: 1.348672 | P147: 0.03 | Q147: =R147*S147 -> 0.0011417556 | R147: =0.019/1000 -> 1.9e-05 | S147: 60.0924 | T147: =F147+Q147+N147 -> 0.0027135679
A148: EU-SRB | B148: 21.005859 | C148: 44.016521 | D148: Base | E148: h2 | F148: =(J148*I148)/(L148*M148) -> 0.0016470408 | G148: 40 | H148: 0.089659303 | I148: =((1+H148)^G148*H148)/((1+H148)^G148-1) -> 0.092646044 | J148: 1600000 | K148: 1000 | L148: 18000 | M148: 5000 | N148: =P148*F148*0.5*(1+O148) -> 5.8025378e-05 | O148: 1.348672 | P148: 0.03 | Q148: =R148*S148 -> 0.0010546843 | R148: =0.019/1000 -> 1.9e-05 | S148: 55.5097 | T148: =F148+Q148+N148 -> 0.0027597505
...

Sheet shipping_collection
A1: Overall info
A2: Lower Heating Values (LHV) | B2: VLSFO | C2: MWh/t | D2: 11.2 | E2: =(F2+D2)/2 -> 11.5 | F2: 11.8
B3: MGO | C3: MWh/t | D3: =42.7/3.6 -> 11.861111 | E3: =(F3+D3)/2 -> 11.902778 | F3: =43/3600*1000 -> 11.944444 | H3: https://www.researchgate.net/publication/305438099_Forecasting_port-level_demand_for_LNG_as_a_ship_fuel_the_case_of_the_port_of_Antwerp
B4: IFO380 | C4: MWh/t | D4: 11.22 | E4: =(F4+D4)/2 -> 11.415 | F4: 11.61 | H4: https://bunkerindex.com/help/article.php?a=21678&h=lng-price-conversion
B5: HFO | C5: MWh/t | D5: =38.3/3.6 -> 10.638889 | E5: =(F5+D5)/2 -> 10.930556 | F5: =40.4/3600*1000 -> 11.222222 | H5: https://www.researchgate.net/publication/305438099_Forecasting_port-level_demand_for_LNG_as_a_ship_fuel_the_case_of_the_port_of_Antwerp
B6: LNG | C6: MWh/t | D6: =48/3600*1000 -> 13.333333 | E6: =(F6+D6)/2 -> 13.472222 | F6: =49/3600*1000 -> 13.611111 | H6: https://www.researchgate.net/publication/305438099_Forecasting_port-level_demand_for_LNG_as_a_ship_fuel_the_case_of_the_port_of_Antwerp
A7: Energy denstiy | B7: H2 (liq) | C7: MWh/t | D7: 33.33 | E7: MWh/m³ | F7: 2.3 | G7: ="-253°C" -> -253°C | H7: https://www.wasserstoff-leitprojekte.de/lw_resource/datapool/systemfiles/elements/files/F4941D1CBA383928E0537E695E862E63/live/document/Wasserstoff-Verfl%C3%BCssigung,_Speicherung,_Transport_und_Anwendung_von_fl%C3%BCssigem_Wasserstoff__2_.pdf | O7: Literature Value | P7: Chosen value
A8: Energy denstiy | B8: H2 | C8: MWh/t | D8: 33.33 | E8: MWh/m³ | F8: 1.4 | G8: 700 bar | H8: https://www.wasserstoff-leitprojekte.de/lw_resource/datapool/systemfiles/elements/files/F4941D1CBA383928E0537E695E862E63/live/document/Wasserstoff-Verfl%C3%BCssigung,_Speicherung,_Transport_und_Anwendung_von_fl%C3%BCssigem_Wasserstoff__2_.pdf | O8: Calculated Value | P8: Chosen value
A9: Energy denstiy | B9: NH3 (liq) | C9: MWh/t | D9: 5.2 | E9: MWh/m³ | F9: 3.6 | H9: https://www.wasserstoff-leitprojekte.de/lw_resource/datapool/systemfiles/elements/files/F4941D1CBA383928E0537E695E862E63/live/document/Wasserstoff-Verfl%C3%BCssigung,_Speicherung,_Transport_und_Anwendung_von_fl%C3%BCssigem_Wasserstoff__2_.pdf | O9: Expert assumption | P9: Chosen value
A10: Energy denstiy | B10: MeOH (liq) | C10: MWh/t | D10: 5.5 | E10: MWh/m³ | F10: 4.4 | O10: AI value | P10: Chosen value
A11: Energy denstiy | B11: SNG | C11: MWh/t | D11: 13.9 | E11: MWh/m³ | F11: 6.6
A12: Energy denstiy | B12: Diesel | C12: MWh/t | D12: 11.9 | E12: MWh/m³ | F12: 9.8 | H12: https://www.wasserstoff-leitprojekte.de/lw_resource/datapool/systemfiles/elements/files/F4941D1CBA383928E0537E695E862E63/live/document/Wasserstoff-Verfl%C3%BCssigung,_Speicherung,_Transport_und_Anwendung_von_fl%C3%BCssigem_Wasserstoff__2_.pdf
A13: Conversion rate | C13: €/$ | D13: 0.88
A14: ETS | B14: 2040 | C14: €/tCo2 | D14: 150 | E14: APS_2040 | F14: https://oa.tib.eu/renate/items/34717383-7179-419d-800d-8a15eff7febb
A15: emission_factor | C15: tCo2/tfuel | D15: =3206/1000 -> 3.206 | E15: =3114/1000 -> 3.114 | F15: https://www.climatiq.io/data/emission-factor/4ee1a3af-8ba4-46a8-9d3c-6198f4e1cc05
C16: tCo2/MWh_fuel | D16: =D15/E2 -> 0.27878261 | E16: =E15/E2 -> 0.27078261
C17: tCo2/TJ | D17: =(79+81.3)/2 -> 80.15 | E17: tCo2/MWh_fuel | F17: =D17/277.78 -> 0.28853769 | G17: CO2 Emission Factors for Fossil Fuels (umweltbundesamt.de)
A18: fuel_costs
A19: VLSFO diesel | B19: 2024 | C19: $/t | D19: 630 | E19: €/MWh_fuel | F19: =D19/E2*D13 -> 48.208696
B20: 2025 | C20: $/t | D20: 585 | E20: €/MWh_fuel | F20: =D20/$E$2*$D$13 -> 44.765217 | AJ20: https://www.sdewes.org/jsdewes/pid12.0484
B21: 2026 | D21: =D34 -> 780.25 | F21: =D21/$E$2*$D$13 -> 59.706087 | AJ21: Radosits et al
A22: Fuel cost Santos | B22: 2022 | C22: €/t_fuel | D22: =682*0.86 -> 586.52 | E22: €/MWh_fuel | F22: =D22/E2 -> 51.001739 | G22: World Bunker Prices - Ship & Bunker (shipandbunker.com)
A23: Fuel cost Rotterdam | B23: 2022 | C23: €/t_fuel | D23: =0.86*638.5 -> 549.11 | E23: €/MWh_fuel | F23: =D23/E2 -> 47.748696 | G23: World Bunker Prices - Ship & Bunker (shipandbunker.com)
A25: fuel_costs_global | B25: Year | D25: VLSFO | E25: MGO | F25: IFO380 | H25: VLSFO | I25: MGO | J25: IFO380
A26: LA/Long Beach | B26: 2026 | C26: $/t | D26: 810 | E26: 1365 | F26: 678 | G26: €/MWh_fuel | H26: =D26*$D$13/$E$2 -> 61.982609 | I26: =E26*$D$13/$E$2 -> 104.45217 | J26: =F26*$D$13/$E$2 -> 51.881739 | K26: World Bunker Prices - Ship & Bunker (shipandbunker.com) | L26: 46237
A27: New York | B27: 2026 | C27: $/t | D27: 724 | E27: 1348 | F27: 540 | G27: €/MWh_fuel | H27: =D27*$D$13/$E$2 -> 55.401739 | I27: =E27*$D$13/$E$2 -> 103.1513 | J27: =F27*$D$13/$E$2 -> 41.321739 | K27: World Bunker Prices - Ship & Bunker (shipandbunker.com) | L27: 46237
A28: Houston | B28: 2026 | C28: $/t | D28: 734 | E28: 1241 | F28: 487 | G28: €/MWh_fuel | H28: =D28*$D$13/$E$2 -> 56.166957 | I28: =E28*$D$13/$E$2 -> 94.963478 | J28: =F28*$D$13/$E$2 -> 37.266087 | K28: World Bunker Prices - Ship & Bunker (shipandbunker.com) | L28: 46237 | Y28: https://www.belfercenter.org/sites/default/files/pantheon_files/files/publication/Report_EU%20Hydrogen_FINAL.pdf
A29: Santos | B29: 2026 | C29: $/t | D29: 815 | E29: 1286 | F29: 511 | G29: €/MWh_fuel | H29: =D29*$D$13/$E$2 -> 62.365217 | I29: =E29*$D$13/$E$2 -> 98.406957 | J29: =F29*$D$13/$E$2 -> 39.102609 | K29: World Bunker Prices - Ship & Bunker (shipandbunker.com) | L29: 46237
A30: Rotterdam | B30: 2026 | C30: $/t | D30: 679 | E30: 1282 | F30: 529 | G30: €/MWh_fuel | H30: =D30*$D$13/$E$2 -> 51.958261 | I30: =E30*$D$13/$E$2 -> 98.10087 | J30: =F30*$D$13/$E$2 -> 40.48 | K30: World Bunker Prices - Ship & Bunker (shipandbunker.com) | L30: 46237
A31: Fujairah | B31: 2026 | C31: $/t | D31: 809 | E31: 1283 | F31: 598 | G31: €/MWh_fuel | H31: =D31*$D$13/$E$2 -> 61.906087 | I31: =E31*$D$13/$E$2 -> 98.177391 | J31: =F31*$D$13/$E$2 -> 45.76 | K31: World Bunker Prices - Ship & Bunker (shipandbunker.com) | L31: 46237
A32: Hong Kong | B32: 2026 | C32: $/t | D32: 833 | E32: 1226 | F32: 623 | G32: €/MWh_fuel | H32: =D32*$D$13/$E$2 -> 63.742609 | I32: =E32*$D$13/$E$2 -> 93.815652 | J32: =F32*$D$13/$E$2 -> 47.673043 | K32: World Bunker Prices - Ship & Bunker (shipandbunker.com) | L32: 46237 | T32: Benchmark Values from Claude
A33: Singapore | B33: 2026 | C33: $/t | D33: 838 | E33: 1226 | F33: 582 | G33: €/MWh_fuel | H33: =D33*$D$13/$E$2 -> 64.125217 | I33: =E33*$D$13/$E$2 -> 93.815652 | J33: =F33*$D$13/$E$2 -> 44.535652 | K33: World Bunker Prices - Ship & Bunker (shipandbunker.com) | L33: 46237
A34: Mean | B34: 2026 | C34: $/t | D34: =AVERAGE(D26:D33) -> 780.25 | E34: =AVERAGE(E26:E33) -> 1282.125 | F34: =AVERAGE(F26:F33) -> 568.5 | G34: €/MWh_fuel | H34: =D34*$D$13/$E$2 -> 59.706087 | I34: =E34*$D$13/$E$2 -> 98.110435 | J34: =F34*$D$13/$E$2 -> 43.502609 | AJ34: https://pdf.sciencedirectassets.com/271472/1-s2.0-S0360319925X00422/1-s2.0-S0360319925012182/main.pdf?X-Amz-Security-Token=IQoJb3JpZ2luX2VjEJD%2F%2F%2F%2F%2F%2F%2F%2F%2F%2FwEaCXVzLWVhc3QtMSJHMEUCIEnsTTcsFowhwLMtYgKYySQzvwOR1LgVWZL4VWq7roAGAiEAy2vQuPGXGs6jSmbA7wK%2FUnpxwFZJ5a5nz0mRyCO2U%2FsqsgUIWBAFGgwwNTkwMDM1NDY4NjUiDDb6vN%2Fm2E9qYf3XdSqPBXPRX4tS1Ejwb12zgy6Z61yG0M1dBYhxACu3%2FqRL%2FMqiCeUO657Hz59TsnddCOTlxz9CBvjstrFjNaN9%2F24J8n3kyfzqdvYmeAIgolT12cQQqbBbZ2%2BEo0FHHsoOQG3mbJY0R2VUDc%2FZWcwjP723i0Vp6zKCNgsNielYuICzXQi8lD27u%2BOuLSjP%2BNg6uNeLnpbVOdI2pVal2xCkJ%2BtubXdvLcrAUtQi1WKOKjSCIlKL%2FtU90UcGIJhyVJaFv03oVL4MZZbf058mAbS53BNCByQz14O%2FMiJUAbQT8BqUyOpogip6aK2XotIoh7bmX%2BmF%2FJ%2F2ylM9thpMBcWDtJl2l5QO7ZRr5r77X8ndpzaKLOKA8KXRsqe7hBTs9HXULUZ%2Fw6Vw4QKUmLj9NTAuXf%2BM5fMlqojeAaIUnIPNjDQmH9LAQPT3tTzkXHPDU%2B7TIDx7KLF%2F3YKheHlO1%2BD0969U%2B7atF8k9Fe2ykLTIS6lq3ND5%2F6Lev4ZCRNnO%2Btg5f1Z%2BMErv8jpIThMt7vayjSgu3QtJ7%2BnDl1zzGGdEKBPeUZmjbFsHBeau4F6O8V7TP8TsBW9jcIaegyIGj7kxRbh0jQPeylbSsKs42dpxOGF1NfUDdxk2VfiLnjZZ%2FQD1O%2BwVPK8qduOnNecaeEBqN2InmSNjnZRg0ZHd5%2FEy5FHaN3SB2qcu33UDh2xZrCWh2R3uWYFh3F2eDf5hrDHjMX7kUvEHfwCRTTW8ZSZp7eKHbJ9TOM87DwHoD5j2N0MTKTC482mJdKSb6xqEMOwHhkiARKYS5KiUFE4CxSmOUk%2FtA1FLNe%2BjE8o0yW98TA%2BPLp2%2FHd%2FBJYDhbG5vHDPxD0lUovcey19wRbU72UZyT%2BCFQ84w9KrI1AY6sQGHjWPcZ6xQj4CrBBfQKgfI7sD4IlP0sBvIPB1B9xvcCLY9NH3dZjh51OdhJeDmxMeD1028aUpTQM85CRytfDAsR%2BIgep8%2Bzmih55w2%2BjI0i5xOWguPwCfvx96jP0cKxnYNd0Od%2F4A9kDPG%2Ff%2FLhEhe8tuVyKqV4e7cfZSvdQjHmDVLaSi3xvGVXp9J%2F7VBd4z%2BvtFdIuA%2FL9VyEdxvrsHJ%2B0iF4NMCFoo%2B9jfdTGoF21E%3D&X-Amz-Algorithm=AWS4-HMAC-SHA256&X-Amz-Date=20260828T232331Z&X-Amz-SignedHeaders=host&X-Amz-Expires=300&X-Amz-Credential=ASIAQ3PHCVTYYACVTZLZ%2F20260828%2Fus-east-1%2Fs3%2Faws4_request&X-Amz-Signature=c05af2d880e4a512daa064ba8c49c7f6f176dfdfdf964a52edd9cd5e8f868fc1&hash=cc12c021dcd96e1b1054e5e13c8f7428c3a84081beae9b3f3c4413f3fa1881a2&host=68042c943591013ac2b2430a89b270f6af2c76d8dfd086a07176afe7c76c2c61&pii=S0360319925012182&tid=spdf-58f8da29-096c-41e5-8aa5-d3c2465a442f&sid=0d4591e34b5b4741081b46a3b13fd5c0c635gxrqb&type=client&tsoh=d3d3LnNjaWVuY2VkaXJlY3QuY29t&rh=d3d3LnNjaWVuY2VkaXJlY3QuY29t&ua=011105505c54575153&rr=a32710719d958804&cc=es
AJ35: Onat & Demir
A36: fuel_costs incl Co2 price | B36: 2026 | C36: €/MWh | D36: =$H$34+$F$17*$D$14 -> 102.98674 | AV36: 0.0378 | AW36: kWh/kgNH3
AV37: =AV36/D9 -> 0.0072692308 | AW37: kWh_el/kWhNH3
A38: Susio Frontier | B38: kn | C38: 13 | D38: World's 1st LH2 carrier Suiso Frontier departs for Australia - Offshore Energy (offshore-energy.biz) | AV38: =1-AV37 -> 0.99273077 | AW38: % energetic efficiency
B39: kn | C39: 30 | D39: IEA The future of hydrogen assumptions
A40: tanker capacity | C40: payload min | D40: payload mean | E40: payload max | G40: payload min | H40: payload mean | I40: payload max
A41: small | B41: m³ | C41: 5000 | D41: =(E41+C41)/2 -> 12500 | E41: 20000 | F41: MWh_h2liq | G41: =C41*$F$7 -> 11500 | H41: =D41*$F$7 -> 28750 | I41: =E41*$F$7 -> 46000 | J41: MWh_nh3 | K41: =C41*$F$9 -> 18000 | L41: =D41*$F$9 -> 45000 | M41: =E41*$F$9 -> 72000 | N41: MWh_MeOH | O41: =C41*$F$10 -> 22000 | P41: =D41*$F$10 -> 55000 | Q41: =E41*$F$10 -> 88000
A42: mid | B42: m³ | C42: 20000 | D42: =(E42+C42)/2 -> 40000 | E42: 60000 | F42: MWh_h2liq | G42: =C42*$F$7 -> 46000 | H42: =D42*$F$7 -> 92000 | I42: =E42*$F$7 -> 138000 | J42: MWh_nh3 | K42: =C42*$F$9 -> 72000 | L42: =D42*$F$9 -> 144000 | M42: =E42*$F$9 -> 216000 | N42: MWh_MeOH | O42: =C42*$F$10 -> 88000 | P42: =D42*$F$10 -> 176000 | Q42: =E42*$F$10 -> 264000
A43: large | B43: m³ | C43: 150000 | D43: =(E43+C43)/2 -> 225000 | E43: 300000 | F43: MWh_h2liq | G43: =C43*$F$7 -> 345000 | H43: =D43*$F$7 -> 517500 | I43: =E43*$F$7 -> 690000 | J43: MWh_nh3 | K43: =C43*$F$9 -> 540000 | L43: =D43*$F$9 -> 810000 | M43: =E43*$F$9 -> 1080000 | N43: MWh_MeOH | O43: =C43*$F$10 -> 660000 | P43: =D43*$F$10 -> 990000 | Q43: =E43*$F$10 -> 1320000
A45: fuel_consumption | B45: kn | C45: 15 | D45: 18 | E45: km/h | F45: =C45*1.852 -> 27.78 | G45: =D45*1.852 -> 33.336 | H45: =E45 -> km/h | I45: =F45 -> 27.78 | J45: =(K45+I45)/2 -> 30.558 | K45: =G45 -> 33.336 | L45: https://en.wikipedia.org/wiki/Knot_(unit)
A46: small | B46: t_fuel/d | C46: 8 | D46: 15 | E46: t/km | F46: =C46/24/F$45 -> 0.01199904 | G46: =D46/24/G$45 -> 0.0187485 | H46: MWh_fuel/km | I46: =F46*$E$2 -> 0.13798896 | J46: =(K46+I46)/2 -> 0.17679836 | K46: =G46*$E$2 -> 0.21560775
A47: mid | B47: t_fuel/d | C47: 15 | D47: 25 | E47: t/km | F47: =C47/24/F$45 -> 0.0224982 | G47: =D47/24/G$45 -> 0.0312475 | H47: MWh_fuel/km | I47: =F47*$E$2 -> 0.2587293 | J47: =(K47+I47)/2 -> 0.30903778 | K47: =G47*$E$2 -> 0.35934625
A48: large | B48: t_fuel/d | C48: 30 | D48: 55 | E48: t/km | F48: =C48/24/F$45 -> 0.0449964 | G48: =D48/24/G$45 -> 0.0687445 | H48: MWh_fuel/km | I48: =F48*$E$2 -> 0.5174586 | J48: =(K48+I48)/2 -> 0.65401018 | K48: =G48*$E$2 -> 0.79056176
C50: H2liq | D50: NH3 | E50: MeOH
A51: Consumption | B51: MWh_fuel/km | C51: =$J$47 -> 0.30903778 | D51: =$J$47 -> 0.30903778 | E51: =$J$47 -> 0.30903778
B52: €/km | C52: =$C$51*$D$36 -> 31.826793 | D52: =$C$51*$D$36 -> 31.826793 | E52: =$C$51*$D$36 -> 31.826793
A53: Transported energy | B53: MWh | C53: =H42 -> 92000 | D53: =L42 -> 144000 | E53: =P42 -> 176000
A54: Spec_consumption | B54: €/km/MWh_transported | C54: =C52/C53 -> 0.00034594341 | D54: =D52/D53 -> 0.0002210194 | E54: =E52/E53 -> 0.00018083405
B56: Boil-off losses | C56: %/d | D56: 0.2 | E56: 0.4
A57: Fuel use | D57: MJ/km | E57: 2500 | F57: 1487 | H57: IEA The future of hydrogen assumptions, Instead use fuel calculation above
D58: MWh/km | E58: =E57/(3.6+10^9) -> 2.5e-06 | F58: =F57/(3.6+10^9) -> 1.487e-06 | H58: IEA The future of hydrogen assumptions, Instead use fuel calculation above
D60: NH3 | E60: H2 liq | F60: MeOH
A61: Seaborne transport | B61: Capacity/ship | C61: tX | D61: 53000 | E61: 11000 | F61: 110000 | G61: IEA The future of hydrogen assumptions
A62: Seaborne transport | B62: Capacity/ship | C62: MWh | D62: =D61*D7 -> 1766490 | E62: =E61*D9 -> 57200 | F62: =F61*D10 -> 605000
A63: Seaborne transport | B63: CAPEX/ship | C63: Mio $ | D63: 85 | E63: 412 | G63: IEA The future of hydrogen assumptions
A64: Seaborne transport | B64: CAPEX/ship | C64: € | D64: =D63*10^6*$D$13 -> 74800000 | E64: =E63*10^6*$D$13 -> 362560000 | F64: =F63*10^6*$D$13 -> 0
A65: Seaborne transport | B65: CAPEX/masse | C65: €/tX | D65: =D64/D61 -> 1411.3208 | E65: =E64/E61 -> 32960 | F65: =F64/F61 -> 0
A66: Seaborne transport | B66: CAPEX | C66: €/MWh_x | D66: =D64/D62 -> 42.343857 | E66: =E64/E62 -> 6338.4615 | F66: =F64/F62 -> 0
A67: Seaborne transport | B67: fom_factor | C67: €/tX/a | D67: 0.04 | E67: 0.04 | F67: 0.04 | G67: IEA The future of hydrogen assumptions
A68: Seaborne transport | B68: Boil off rate | D68: - | E68: 0.002 | F68: - | G68: IEA The future of hydrogen assumptions
A69: Seaborne transport | B69: Flash rate | D69: - | E69: 0.013 | F69: - | G69: IEA The future of hydrogen assumptions
A70: Seaborne transport | B70: Full load hours | C70: h | D70: =8760/2 -> 4380 | E70: =8760/2 -> 4380 | F70: =8760/2 -> 4380
A71: Seaborne transport | B71: Capacity/ship | C71: t | D71: 53000 | E71: 11000
A72: Seaborne transport | C72: MWh | D72: =D71*$D$7 -> 1766490 | E72: =E71*$D$7 -> 366630
A73: Seaborne transport | B73: CAPEX | C73: €/MW | D73: =D63*10^6*$D$13/D72*D70 -> 185466.09 | E73: =E63*10^6*$D$13/E72*E70 -> 4331377.1
A74: Seaborne transport | B74: Ship speed | C74: km/h | D74: 30 | E74: 30
A75: Seaborne transport | B75: annual OPEX | D75: 0.04 | E75: 0.04
A76: Seaborne transport | B76: Boil-off rate | C76: 1/d | D76: 0 | E76: 0.002 | F76: 0 | G76: IEA The future of hydrogen assumptions
A77: Seaborne transport | B77: Flash rate | D77: 0 | E77: 0.013 | F77: 0 | G77: IEA The future of hydrogen assumptions
B79: Terminal calculations | D79: NH3 | E79: H2 liq | F79: MeOH
A80: Export terminal | B80: Energy content | C80: MWh | D80: =D81*D9 -> 177320 | E80: =E81*D8 -> 106322.7
A81: Export terminal | B81: Capacity/tank | C81: tX | D81: 34100 | E81: 3190 | G81: IEA The future of hydrogen assumptions
A82: Export terminal | B82: CAPEX/tank | C82: € | D82: =0.86*68000000 -> 58480000 | E82: =0.86*290000000 -> 249400000 | G82: IEA The future of hydrogen assumptions
A83: Export terminal | B83: CAPEX/masse | C83: €/tX | D83: =D82/D81 -> 1714.956 | E83: =E82/E81 -> 78181.818 | G83: berechnet
A84: Export terminal | B84: fom_factor | C84: %_CAPEX/tX/a | D84: 0.04 | E84: 0.04 | F84: 0.04 | G84: IEA The future of hydrogen assumptions
A85: Export terminal | B85: fom | C85: €/tX/a | D85: =D84*D83 -> 68.59824 | E85: =E84*E83 -> 3127.2727 | G85: berechnet als 4% vom CAPEX laut Studie
A86: Export terminal | B86: Electricity use | C86: kWh/kgH2 | D86: 0.005 | E86: 0.61 | F86: 0.01 | G86: IEA The future of hydrogen assumptions
A87: Export terminal | B87: Boil off rate | C87: %/day | E87: 0.001 | G87: IEA The future of hydrogen assumptions
A88: Export terminal | B88: Flash rate | C88: % | E88: 0.001 | G88: IEA The future of hydrogen assumptions
A90: Import terminal | B90: Capacity/tank | C90: tX | D90: 56700 | E90: 3550 | F90: 61600 | G90: IEA The future of hydrogen assumptions
A91: Import terminal | B91: CAPEX/tank | C91: € | D91: =97000000*0.86 -> 83420000 | E91: =320000000*0.86 -> 275200000 | F91: =35000000*0.86 -> 30100000 | G91: IEA The future of hydrogen assumptions
A92: Import terminal | B92: CAPEX | C92: €/tX | D92: =D91/D90 -> 1471.2522 | E92: =E91/E90 -> 77521.127 | F92: =F91/F90 -> 488.63636 | G92: IEA The future of hydrogen assumptions
A93: Import terminal | C93: €/tX/a | D93: =D92*0.04 -> 58.850088 | E93: =E92*0.04 -> 3100.8451 | F93: =F92*0.04 -> 19.545455 | G93: berechnet als 4% vom CAPEX/masse
A94: Import terminal | B94: Electricity use | C94: MWh/tH2 | D94: 0.02 | E94: 0.2 | F94: 0.01 | G94: IEA The future of hydrogen assumptions
A95: Import terminal | B95: Boil off rate | C95: %/day | E95: 0.1 | G95: IEA The future of hydrogen assumptions
D97: Today | E97: 2030 | F97: long term
A98: Electrolysis | B98: CAPEX | C98: $/kWel | D98: 900 | E98: 700 | F98: 450 | G98: https://iea.blob.core.windows.net/assets/29b027e5-fefc-47df-aed0-456b1bb38844/IEA-The-Future-of-Hydrogen-Assumptions-Annex_CORR.pdf
A99: Electrolysis | B99: CAPEX | C99: €/MW | D99: =D98*$D$13*1000 -> 792000 | E99: =E98*$D$13*1000 -> 616000 | F99: =F98*$D$13*1000 -> 396000
A100: Electrolysis | B100: efficiency | D100: 0.64 | E100: 0.69 | F100: 0.74 | G100: https://iea.blob.core.windows.net/assets/29b027e5-fefc-47df-aed0-456b1bb38844/IEA-The-Future-of-Hydrogen-Assumptions-Annex_CORR.pdf
A101: Electrolysis | B101: annual OPEX | C101: %CAPEX/a | D101: 0.015 | E101: 0.015 | F101: 0.015 | G101: https://iea.blob.core.windows.net/assets/29b027e5-fefc-47df-aed0-456b1bb38844/IEA-The-Future-of-Hydrogen-Assumptions-Annex_CORR.pdf
A102: Electrolysis | B102: lifetime | C102: h | D102: 95000 | E102: 95000 | F102: 100000 | G102: https://iea.blob.core.windows.net/assets/29b027e5-fefc-47df-aed0-456b1bb38844/IEA-The-Future-of-Hydrogen-Assumptions-Annex_CORR.pdf
A103: Electrolysis | B103: lifetime | C103: a | D103: =D102/5000 -> 19 | E103: =E102/5000 -> 19 | F103: =F102/5000 -> 20 | G103: https://iea.blob.core.windows.net/assets/29b027e5-fefc-47df-aed0-456b1bb38844/IEA-The-Future-of-Hydrogen-Assumptions-Annex_CORR.pdf
D104: Today | E104: 2030 | F104: long term
A105: Methanation | B105: CAPEX | C105: $/kWprod | D105: 890 | E105: 760 | F105: 565 | G105: https://iea.blob.core.windows.net/assets/29b027e5-fefc-47df-aed0-456b1bb38844/IEA-The-Future-of-Hydrogen-Assumptions-Annex_CORR.pdf
A106: Methanation | B106: CAPEX | C106: €/MW | D106: =D105*$D$13*1000 -> 783200 | E106: =E105*$D$13*1000 -> 668800 | F106: =F105*$D$13*1000 -> 497200
A107: Methanation | B107: efficiency | D107: 0.77 | E107: 0.77 | F107: 0.77 | G107: https://iea.blob.core.windows.net/assets/29b027e5-fefc-47df-aed0-456b1bb38844/IEA-The-Future-of-Hydrogen-Assumptions-Annex_CORR.pdf
A108: Methanation | B108: efficiency
...

Sheet shipping_compact
D1: invest_cost | E1: full_load_hours | F1: lifetime | G1: efficiency_substantial | H1: efficiency_energetic | I1: efficiency_dynamic | J1: fom_factor | K1: electricity_consumption | L1: fuel_consumption
A2: transport_commodity | B2: process | C2: generalisation | D2: €/MW | E2: h/a | F2: a | G2: - | H2: - | I2: %/km | J2: %/invest_cost | K2: MWh_el/MWh_x | L2: MWh_fuel/MWh_x
A3: h2liq | B3: Liquefaction | C3: Conversion | D3: 938550 | E3: 6000 | F3: 30 | G3: 0.98 | H3: 0.7449745 | J3: 0.0325 | K3: 0 | N3: final values
A4: h2liq | B4: Port Storage
A5: h2liq | B5: Export Terminal
A6: h2liq | B6: Import Terminal
A7: h2liq | C7: Terminal | D7: 14340589 | E7: 6000 | F7: 30 | G7: 1 | H7: 1 | J7: 0.04 | K7: 0
A8: h2liq | C8: Shipping | D8: 144364800 | E8: 4380 | F8: 25 | G8: 0.987 | H8: 1 | I8: =0.002/720 -> 2.7777778e-06 | J8: 0.04 | L8: 0.00034594341
A9: h2liq | B9: Regasification | C9: Reconversion | D9: 226010 | E9: 6000 | F9: 30 | G9: 0.98 | H9: 0.98 | J9: 0.03 | K9: 0.0060006001
A10: nh3 | B10: ASU | D10: 4143791 | G10: 1 | J10: 0.03 | K10: 0.0399
A11: nh3 | B11: Haber_Bosch | D11: 1842989 | G11: 0.99 | H11: 0.871 | J11: 0.03 | K11: 0.2473
A12: nh3 | B12: Synthesis | C12: Conversion | D12: =SUM(D10:D11) -> 5986780 | E12: 6000 | F12: 30 | G12: 0.85 | H12: 0.992 | J12: 0.05 | K12: =SUM(K10:K11) -> 0.2872
A13: nh3 | B13: Port Storage
A14: nh3 | B14: Export Terminal
A15: nh3 | B15: Import Terminal
A16: nh3 | C16: Terminal | D16: 293456.89 | E16: 6000 | F16: 30 | G16: 1 | H16: 1 | J16: 0.04 | K16: 0
A17: nh3 | C17: Shipping | D17: 6181584.9 | E17: 4380 | F17: 25 | G17: 1 | H17: 1 | I17: 0 | J17: 0.04 | L17: 0.0002210194
A18: nh3 | B18: Cracking | C18: Reconversion | D18: 1418767 | E18: 6000 | F18: 30 | G18: 0.996 | H18: 0.685 | J18: 0.043 | K18: 0
A19: ch3oh | B19: Methanation | D19: 3500000 | G19: 0.75
A20: ch3oh | B20: Methanolsation | D20: 3800000 | G20: 0.79
A21: ch3oh | B21: Synthesis | C21: Conversion | D21: =SUM(D19:D20) -> 7300000 | E21: 6000 | F21: 30 | G21: =G20*G19 -> 0.5925 | H21: 1 | J21: 0.04
A22: ch3oh | B22: Port Storage
A23: ch3oh | B23: Export Terminal
A24: ch3oh | B24: Import Terminal
A25: ch3oh | C25: Terminal | D25: =D16 -> 293456.89 | E25: 6000 | F25: 30 | G25: 1 | H25: 1 | J25: 0.04 | K25: 0.271
A26: ch3oh | C26: Shipping | D26: 1756697 | E26: 4380 | F26: 25 | G26: 1 | H26: 1 | I26: 0 | J26: 0.04 | L26: 0.00018083405
A27: ch3oh | B27: Cracking | C27: Reconversion | D27: 22653 | E27: 6000 | F27: 30 | G27: 0.99 | H27: 0.833 | J27: 0.04 | K27: 0

Sheet shipping_data
A1: terminal_name | B1: commodity | C1: name | D1: node | E1: lat | F1: lon | G1: alternative | H1: conversion_invest_cost | I1: full_load_hours | J1: conversion_lifetime | K1: conversion_efficiency_substantial | L1: conversion_efficiency_energetic | M1: conversion_fom_capex_factor | N1: electricity_per_energy_converted | O1: terminal_invest_cost | P1: terminal_lifetime | Q1: terminal_efficiency | R1: terminal_fom_capex_factor | S1: electricity_per_energy_loaded | T1: shipping_invest_cost | U1: shipping_full_load_hours | V1: shipping_lifetime | W1: shipping_efficiency_flat | X1: shipping_efficiency_km | Y1: shipping_fom_capex_factor | Z1: fuel_consumption_km | AA1: reconversion_invest_cost | AB1: reconversion_lifetime | AC1: reconversion_efficiency_substantial | AD1: reconversion_efficiency_energetic | AE1: reconversion_fom_capex_factor | AF1: electricity_per_energy_reconverted
A2: terminal_EU-NLD | B2: h2liq | C2: =_xlfn.CONCAT(B2,"_",A2) -> h2liq_terminal_EU-NLD | D2: EU-NLD | E2: 51.948455 | F2: 4.140296 | G2: Base | H2: =shipping_compact!D$3 -> 938550 | I2: =shipping_compact!E$3 -> 6000 | J2: =shipping_compact!F$3 -> 30 | K2: =shipping_compact!G$3 -> 0.98 | L2: =shipping_compact!H$3 -> 0.7449745 | M2: =shipping_compact!J$3 -> 0.0325 | N2: =shipping_compact!K$3 -> 0 | O2: =shipping_compact!D$7 -> 14340589 | P2: =shipping_compact!F$7 -> 30 | Q2: =shipping_compact!G$7 -> 1 | R2: =shipping_compact!J$7 -> 0.04 | S2: =shipping_compact!L$7 -> 0 | T2: =shipping_compact!D$8 -> 144364800 | U2: =shipping_compact!E$8 -> 4380 | V2: =shipping_compact!F$8 -> 25 | W2: =shipping_compact!G$8 -> 0.987 | X2: =shipping_compact!I$8 -> 2.7777778e-06 | Y2: =shipping_compact!J$8 -> 0.04 | Z2: =shipping_compact!L$8 -> 0.00034594341 | AA2: =shipping_compact!D$9 -> 226010 | AB2: =shipping_compact!F$9 -> 30 | AC2: =shipping_compact!G$9 -> 0.98 | AD2: =shipping_compact!H$9 -> 0.98 | AE2: =shipping_compact!J$9 -> 0.03 | AF2: =shipping_compact!K$9 -> 0.0060006001
A3: terminal_EU-PRT | B3: h2liq | C3: =_xlfn.CONCAT(B3,"_",A3) -> h2liq_terminal_EU-PRT | D3: EU-PRT | E3: 37.961098 | F3: -8.8786877 | G3: Base | H3: =shipping_compact!$D$3 -> 938550 | I3: =shipping_compact!E$3 -> 6000 | J3: =shipping_compact!F$3 -> 30 | K3: =shipping_compact!G$3 -> 0.98 | L3: =shipping_compact!H$3 -> 0.7449745 | M3: =shipping_compact!J$3 -> 0.0325 | N3: =shipping_compact!K$3 -> 0 | O3: =shipping_compact!D$7 -> 14340589 | P3: =shipping_compact!F$7 -> 30 | Q3: =shipping_compact!G$7 -> 1 | R3: =shipping_compact!J$7 -> 0.04 | S3: =shipping_compact!L$7 -> 0 | T3: =shipping_compact!D$8 -> 144364800 | U3: =shipping_compact!E$8 -> 4380 | V3: =shipping_compact!F$8 -> 25 | W3: =shipping_compact!G$8 -> 0.987 | X3: =shipping_compact!I$8 -> 2.7777778e-06 | Y3: =shipping_compact!J$8 -> 0.04 | Z3: =shipping_compact!L$8 -> 0.00034594341 | AA3: =shipping_compact!D$9 -> 226010 | AB3: =shipping_compact!F$9 -> 30 | AC3: =shipping_compact!G$9 -> 0.98 | AD3: =shipping_compact!H$9 -> 0.98 | AE3: =shipping_compact!J$9 -> 0.03 | AF3: =shipping_compact!K$9 -> 0.0060006001
A4: terminal_EU-ESP | B4: h2liq | C4: =_xlfn.CONCAT(B4,"_",A4) -> h2liq_terminal_EU-ESP | D4: EU-ESP | E4: 39.463713 | F4: -0.35881979 | G4: Base | H4: =shipping_compact!$D$3 -> 938550 | I4: =shipping_compact!E$3 -> 6000 | J4: =shipping_compact!F$3 -> 30 | K4: =shipping_compact!G$3 -> 0.98 | L4: =shipping_compact!H$3 -> 0.7449745 | M4: =shipping_compact!J$3 -> 0.0325 | N4: =shipping_compact!K$3 -> 0 | O4: =shipping_compact!D$7 -> 14340589 | P4: =shipping_compact!F$7 -> 30 | Q4: =shipping_compact!G$7 -> 1 | R4: =shipping_compact!J$7 -> 0.04 | S4: =shipping_compact!L$7 -> 0 | T4: =shipping_compact!D$8 -> 144364800 | U4: =shipping_compact!E$8 -> 4380 | V4: =shipping_compact!F$8 -> 25 | W4: =shipping_compact!G$8 -> 0.987 | X4: =shipping_compact!I$8 -> 2.7777778e-06 | Y4: =shipping_compact!J$8 -> 0.04 | Z4: =shipping_compact!L$8 -> 0.00034594341 | AA4: =shipping_compact!D$9 -> 226010 | AB4: =shipping_compact!F$9 -> 30 | AC4: =shipping_compact!G$9 -> 0.98 | AD4: =shipping_compact!H$9 -> 0.98 | AE4: =shipping_compact!J$9 -> 0.03 | AF4: =shipping_compact!K$9 -> 0.0060006001
A5: terminal_EU-ISL | B5: h2liq | C5: =_xlfn.CONCAT(B5,"_",A5) -> h2liq_terminal_EU-ISL | D5: EU-ISL | E5: 64.094858 | F5: -21.853528 | G5: Base | H5: =shipping_compact!$D$3 -> 938550 | I5: =shipping_compact!E$3 -> 6000 | J5: =shipping_compact!F$3 -> 30 | K5: =shipping_compact!G$3 -> 0.98 | L5: =shipping_compact!H$3 -> 0.7449745 | M5: =shipping_compact!J$3 -> 0.0325 | N5: =shipping_compact!K$3 -> 0 | O5: =shipping_compact!D$7 -> 14340589 | P5: =shipping_compact!F$7 -> 30 | Q5: =shipping_compact!G$7 -> 1 | R5: =shipping_compact!J$7 -> 0.04 | S5: =shipping_compact!L$7 -> 0 | T5: =shipping_compact!D$8 -> 144364800 | U5: =shipping_compact!E$8 -> 4380 | V5: =shipping_compact!F$8 -> 25 | W5: =shipping_compact!G$8 -> 0.987 | X5: =shipping_compact!I$8 -> 2.7777778e-06 | Y5: =shipping_compact!J$8 -> 0.04 | Z5: =shipping_compact!L$8 -> 0.00034594341 | AA5: =shipping_compact!D$9 -> 226010 | AB5: =shipping_compact!F$9 -> 30 | AC5: =shipping_compact!G$9 -> 0.98 | AD5: =shipping_compact!H$9 -> 0.98 | AE5: =shipping_compact!J$9 -> 0.03 | AF5: =shipping_compact!K$9 -> 0.0060006001
A6: terminal_EU-ITA4 | B6: h2liq | C6: =_xlfn.CONCAT(B6,"_",A6) -> h2liq_terminal_EU-ITA4 | D6: EU-ITA4 | E6: 45.205817 | F6: 12.293656 | G6: Base | H6: =shipping_compact!$D$3 -> 938550 | I6: =shipping_compact!E$3 -> 6000 | J6: =shipping_compact!F$3 -> 30 | K6: =shipping_compact!G$3 -> 0.98 | L6: =shipping_compact!H$3 -> 0.7449745 | M6: =shipping_compact!J$3 -> 0.0325 | N6: =shipping_compact!K$3 -> 0 | O6: =shipping_compact!D$7 -> 14340589 | P6: =shipping_compact!F$7 -> 30 | Q6: =shipping_compact!G$7 -> 1 | R6: =shipping_compact!J$7 -> 0.04 | S6: =shipping_compact!L$7 -> 0 | T6: =shipping_compact!D$8 -> 144364800 | U6: =shipping_compact!E$8 -> 4380 | V6: =shipping_compact!F$8 -> 25 | W6: =shipping_compact!G$8 -> 0.987 | X6: =shipping_compact!I$8 -> 2.7777778e-06 | Y6: =shipping_compact!J$8 -> 0.04 | Z6: =shipping_compact!L$8 -> 0.00034594341 | AA6: =shipping_compact!D$9 -> 226010 | AB6: =shipping_compact!F$9 -> 30 | AC6: =shipping_compact!G$9 -> 0.98 | AD6: =shipping_compact!H$9 -> 0.98 | AE6: =shipping_compact!J$9 -> 0.03 | AF6: =shipping_compact!K$9 -> 0.0060006001
A7: terminal_EU-ITA | B7: h2liq | C7: =_xlfn.CONCAT(B7,"_",A7) -> h2liq_terminal_EU-ITA | D7: EU-ITA | E7: 45.205817 | F7: 12.293656 | G7: Base | H7: =shipping_compact!$D$3 -> 938550 | I7: =shipping_compact!E$3 -> 6000 | J7: =shipping_compact!F$3 -> 30 | K7: =shipping_compact!G$3 -> 0.98 | L7: =shipping_compact!H$3 -> 0.7449745 | M7: =shipping_compact!J$3 -> 0.0325 | N7: =shipping_compact!K$3 -> 0 | O7: =shipping_compact!D$7 -> 14340589 | P7: =shipping_compact!F$7 -> 30 | Q7: =shipping_compact!G$7 -> 1 | R7: =shipping_compact!J$7 -> 0.04 | S7: =shipping_compact!L$7 -> 0 | T7: =shipping_compact!D$8 -> 144364800 | U7: =shipping_compact!E$8 -> 4380 | V7: =shipping_compact!F$8 -> 25 | W7: =shipping_compact!G$8 -> 0.987 | X7: =shipping_compact!I$8 -> 2.7777778e-06 | Y7: =shipping_compact!J$8 -> 0.04 | Z7: =shipping_compact!L$8 -> 0.00034594341 | AA7: =shipping_compact!D$9 -> 226010 | AB7: =shipping_compact!F$9 -> 30 | AC7: =shipping_compact!G$9 -> 0.98 | AD7: =shipping_compact!H$9 -> 0.98 | AE7: =shipping_compact!J$9 -> 0.03 | AF7: =shipping_compact!K$9 -> 0.0060006001
A8: terminal_AS-TUR | B8: h2liq | C8: =_xlfn.CONCAT(B8,"_",A8) -> h2liq_terminal_AS-TUR | D8: AS-TUR | E8: 36.825941 | F8: 36.177898 | G8: Base | H8: =shipping_compact!$D$3 -> 938550 | I8: =shipping_compact!E$3 -> 6000 | J8: =shipping_compact!F$3 -> 30 | K8: =shipping_compact!G$3 -> 0.98 | L8: =shipping_compact!H$3 -> 0.7449745 | M8: =shipping_compact!J$3 -> 0.0325 | N8: =shipping_compact!K$3 -> 0 | O8: =shipping_compact!D$7 -> 14340589 | P8: =shipping_compact!F$7 -> 30 | Q8: =shipping_compact!G$7 -> 1 | R8: =shipping_compact!J$7 -> 0.04 | S8: =shipping_compact!L$7 -> 0 | T8: =shipping_compact!D$8 -> 144364800 | U8: =shipping_compact!E$8 -> 4380 | V8: =shipping_compact!F$8 -> 25 | W8: =shipping_compact!G$8 -> 0.987 | X8: =shipping_compact!I$8 -> 2.7777778e-06 | Y8: =shipping_compact!J$8 -> 0.04 | Z8: =shipping_compact!L$8 -> 0.00034594341 | AA8: =shipping_compact!D$9 -> 226010 | AB8: =shipping_compact!F$9 -> 30 | AC8: =shipping_compact!G$9 -> 0.98 | AD8: =shipping_compact!H$9 -> 0.98 | AE8: =shipping_compact!J$9 -> 0.03 | AF8: =shipping_compact!K$9 -> 0.0060006001
A9: terminal_EU-SWE3 | B9: h2liq | C9: =_xlfn.CONCAT(B9,"_",A9) -> h2liq_terminal_EU-SWE3 | D9: EU-SWE3 | E9: 58.913025 | F9: 17.96051 | G9: Base | H9: =shipping_compact!$D$3 -> 938550 | I9: =shipping_compact!E$3 -> 6000 | J9: =shipping_compact!F$3 -> 30 | K9: =shipping_compact!G$3 -> 0.98 | L9: =shipping_compact!H$3 -> 0.7449745 | M9: =shipping_compact!J$3 -> 0.0325 | N9: =shipping_compact!K$3 -> 0 | O9: =shipping_compact!D$7 -> 14340589 | P9: =shipping_compact!F$7 -> 30 | Q9: =shipping_compact!G$7 -> 1 | R9: =shipping_compact!J$7 -> 0.04 | S9: =shipping_compact!L$7 -> 0 | T9: =shipping_compact!D$8 -> 144364800 | U9: =shipping_compact!E$8 -> 4380 | V9: =shipping_compact!F$8 -> 25 | W9: =shipping_compact!G$8 -> 0.987 | X9: =shipping_compact!I$8 -> 2.7777778e-06 | Y9: =shipping_compact!J$8 -> 0.04 | Z9: =shipping_compact!L$8 -> 0.00034594341 | AA9: =shipping_compact!D$9 -> 226010 | AB9: =shipping_compact!F$9 -> 30 | AC9: =shipping_compact!G$9 -> 0.98 | AD9: =shipping_compact!H$9 -> 0.98 | AE9: =shipping_compact!J$9 -> 0.03 | AF9: =shipping_compact!K$9 -> 0.0060006001
A10: terminal_EU-SWE | B10: h2liq | C10: =_xlfn.CONCAT(B10,"_",A10) -> h2liq_terminal_EU-SWE | D10: EU-SWE | E10: 58.913025 | F10: 17.96051 | G10: Base | H10: =shipping_compact!$D$3 -> 938550 | I10: =shipping_compact!E$3 -> 6000 | J10: =shipping_compact!F$3 -> 30 | K10: =shipping_compact!G$3 -> 0.98 | L10: =shipping_compact!H$3 -> 0.7449745 | M10: =shipping_compact!J$3 -> 0.0325 | N10: =shipping_compact!K$3 -> 0 | O10: =shipping_compact!D$7 -> 14340589 | P10: =shipping_compact!F$7 -> 30 | Q10: =shipping_compact!G$7 -> 1 | R10: =shipping_compact!J$7 -> 0.04 | S10: =shipping_compact!L$7 -> 0 | T10: =shipping_compact!D$8 -> 144364800 | U10: =shipping_compact!E$8 -> 4380 | V10: =shipping_compact!F$8 -> 25 | W10: =shipping_compact!G$8 -> 0.987 | X10: =shipping_compact!I$8 -> 2.7777778e-06 | Y10: =shipping_compact!J$8 -> 0.04 | Z10: =shipping_compact!L$8 -> 0.00034594341 | AA10: =shipping_compact!D$9 -> 226010 | AB10: =shipping_compact!F$9 -> 30 | AC10: =shipping_compact!G$9 -> 0.98 | AD10: =shipping_compact!H$9 -> 0.98 | AE10: =shipping_compact!J$9 -> 0.03 | AF10: =shipping_compact!K$9 -> 0.0060006001
A11: terminal_EU-GBR | B11: h2liq | C11: =_xlfn.CONCAT(B11,"_",A11) -> h2liq_terminal_EU-GBR | D11: EU-GBR | E11: 51.70829 | F11: -5.0646298 | G11: Base | H11: =shipping_compact!$D$3 -> 938550 | I11: =shipping_compact!E$3 -> 6000 | J11: =shipping_compact!F$3 -> 30 | K11: =shipping_compact!G$3 -> 0.98 | L11: =shipping_compact!H$3 -> 0.7449745 | M11: =shipping_compact!J$3 -> 0.0325 | N11: =shipping_compact!K$3 -> 0 | O11: =shipping_compact!D$7 -> 14340589 | P11: =shipping_compact!F$7 -> 30 | Q11: =shipping_compact!G$7 -> 1 | R11: =shipping_compact!J$7 -> 0.04 | S11: =shipping_compact!L$7 -> 0 | T11: =shipping_compact!D$8 -> 144364800 | U11: =shipping_compact!E$8 -> 4380 | V11: =shipping_compact!F$8 -> 25 | W11: =shipping_compact!G$8 -> 0.987 | X11: =shipping_compact!I$8 -> 2.7777778e-06 | Y11: =shipping_compact!J$8 -> 0.04 | Z11: =shipping_compact!L$8 -> 0.00034594341 | AA11: =shipping_compact!D$9 -> 226010 | AB11: =shipping_compact!F$9 -> 30 | AC11: =shipping_compact!G$9 -> 0.98 | AD11: =shipping_compact!H$9 -> 0.98 | AE11: =shipping_compact!J$9 -> 0.03 | AF11: =shipping_compact!K$9 -> 0.0060006001
A12: terminal_AS-QAT | B12: h2liq | C12: =_xlfn.CONCAT(B12,"_",A12) -> h2liq_terminal_AS-QAT | D12: AS-QAT | E12: 25.883521 | F12: 51.480261 | G12: Base | H12: =shipping_compact!$D$3 -> 938550 | I12: =shipping_compact!E$3 -> 6000 | J12: =shipping_compact!F$3 -> 30 | K12: =shipping_compact!G$3 -> 0.98 | L12: =shipping_compact!H$3 -> 0.7449745 | M12: =shipping_compact!J$3 -> 0.0325 | N12: =shipping_compact!K$3 -> 0 | O12: =shipping_compact!D$7 -> 14340589 | P12: =shipping_compact!F$7 -> 30 | Q12: =shipping_compact!G$7 -> 1 | R12: =shipping_compact!J$7 -> 0.04 | S12: =shipping_compact!L$7 -> 0 | T12: =shipping_compact!D$8 -> 144364800 | U12: =shipping_compact!E$8 -> 4380 | V12: =shipping_compact!F$8 -> 25 | W12: =shipping_compact!G$8 -> 0.987 | X12: =shipping_compact!I$8 -> 2.7777778e-06 | Y12: =shipping_compact!J$8 -> 0.04 | Z12: =shipping_compact!L$8 -> 0.00034594341 | AA12: =shipping_compact!D$9 -> 226010 | AB12: =shipping_compact!F$9 -> 30 | AC12: =shipping_compact!G$9 -> 0.98 | AD12: =shipping_compact!H$9 -> 0.98 | AE12: =shipping_compact!J$9 -> 0.03 | AF12: =shipping_compact!K$9 -> 0.0060006001
A13: terminal_AS-IND-WE | B13: h2liq | C13: =_xlfn.CONCAT(B13,"_",A13) -> h2liq_terminal_AS-IND-WE | D13: AS-IND | E13: 18.944742 | F13: 72.950074 | G13: Base | H13: =shipping_compact!$D$3 -> 938550 | I13: =shipping_compact!E$3 -> 6000 | J13: =shipping_compact!F$3 -> 30 | K13: =shipping_compact!G$3 -> 0.98 | L13: =shipping_compact!H$3 -> 0.7449745 | M13: =shipping_compact!J$3 -> 0.0325 | N13: =shipping_compact!K$3 -> 0 | O13: =shipping_compact!D$7 -> 14340589 | P13: =shipping_compact!F$7 -> 30 | Q13: =shipping_compact!G$7 -> 1 | R13: =shipping_compact!J$7 -> 0.04 | S13: =shipping_compact!L$7 -> 0 | T13: =shipping_compact!D$8 -> 144364800 | U13: =shipping_compact!E$8 -> 4380 | V13: =shipping_compact!F$8 -> 25 | W13: =shipping_compact!G$8 -> 0.987 | X13: =shipping_compact!I$8 -> 2.7777778e-06 | Y13: =shipping_compact!J$8 -> 0.04 | Z13: =shipping_compact!L$8 -> 0.00034594341 | AA13: =shipping_compact!D$9 -> 226010 | AB13: =shipping_compact!F$9 -> 30 | AC13: =shipping_compact!G$9 -> 0.98 | AD13: =shipping_compact!H$9 -> 0.98 | AE13: =shipping_compact!J$9 -> 0.03 | AF13: =shipping_compact!K$9 -> 0.0060006001
A14: terminal_AS-IND-WE | B14: h2liq | C14: =_xlfn.CONCAT(B14,"_",A14) -> h2liq_terminal_AS-IND-WE | D14: AS-IND-WE | E14: 18.944742 | F14: 72.950074 | G14: Base | H14: =shipping_compact!$D$3 -> 938550 | I14: =shipping_compact!E$3 -> 6000 | J14: =shipping_compact!F$3 -> 30 | K14: =shipping_compact!G$3 -> 0.98 | L14: =shipping_compact!H$3 -> 0.7449745 | M14: =shipping_compact!J$3 -> 0.0325 | N14: =shipping_compact!K$3 -> 0 | O14: =shipping_compact!D$7 -> 14340589 | P14: =shipping_compact!F$7 -> 30 | Q14: =shipping_compact!G$7 -> 1 | R14: =shipping_compact!J$7 -> 0.04 | S14: =shipping_compact!L$7 -> 0 | T14: =shipping_compact!D$8 -> 144364800 | U14: =shipping_compact!E$8 -> 4380 | V14: =shipping_compact!F$8 -> 25 | W14: =shipping_compact!G$8 -> 0.987 | X14: =shipping_compact!I$8 -> 2.7777778e-06 | Y14: =shipping_compact!J$8 -> 0.04 | Z14: =shipping_compact!L$8 -> 0.00034594341 | AA14: =shipping_compact!D$9 -> 226010 | AB14: =shipping_compact!F$9 -> 30 | AC14: =shipping_compact!G$9 -> 0.98 | AD14: =shipping_compact!H$9 -> 0.98 | AE14: =shipping_compact!J$9 -> 0.03 | AF14: =shipping_compact!K$9 -> 0.0060006001
... A49: terminal_AF-EGY | B49: h2liq | C49: =_xlfn.CONCAT(B49,"_",A49) -> h2liq_terminal_AF-EGY | D49: AF-EGY | E49: 29.916289 | F49: 32.449177 | G49: Base | H49: =shipping_compact!$D$3 -> 938550 | I49: =shipping_compact!E$3 -> 6000 | J49: =shipping_compact!F$3 -> 30 | K49: =shipping_compact!G$3 -> 0.98 | L49: =shipping_compact!H$3 -> 0.7449745 | M49: =shipping_compact!J$3 -> 0.0325 | N49: =shipping_compact!K$3 -> 0 | O49: =shipping_compact!D$7 -> 14340589 | P49: =shipping_compact!F$7 -> 30 | Q49: =shipping_compact!G$7 -> 1 | R49: =shipping_compact!J$7 -> 0.04 | S49: =shipping_compact!L$7 -> 0 | T49: =shipping_compact!D$8 -> 144364800 | U49: =shipping_compact!E$8 -> 4380 | V49: =shipping_compact!F$8 -> 25 | W49: =shipping_compact!G$8 -> 0.987 | X49: =shipping_compact!I$8 -> 2.7777778e-06 | Y49: =shipping_compact!J$8 -> 0.04 | Z49: =shipping_compact!L$8 -> 0.00034594341 | AA49: =shipping_compact!D$9 -> 226010 | AB49: =shipping_compact!F$9 -> 30 | AC49: =shipping_compact!G$9 -> 0.98 | AD49: =shipping_compact!H$9 -> 0.98 | AE49: =shipping_compact!J$9 -> 0.03 | AF49: =shipping_compact!K$9 -> 0.0060006001
A50: terminal_EU-NLD | B50: nh3 | C50: =_xlfn.CONCAT(B50,"_",A50) -> nh3_terminal_EU-NLD | D50: EU-NLD | E50: 51.948455 | F50: 4.140296 | G50: Base | H50: =shipping_compact!D$12 -> 5986780 | I50: =shipping_compact!E$12 -> 6000 | J50: =shipping_compact!F$12 -> 30 | K50: =shipping_compact!G$12 -> 0.85 | L50: =shipping_compact!H$12 -> 0.992 | M50: =shipping_compact!J$12 -> 0.05 | N50: =shipping_compact!K$12 -> 0.2872 | O50: =shipping_compact!D$16 -> 293456.89 | P50: =shipping_compact!F$16 -> 30 | Q50: =shipping_compact!G$16 -> 1 | R50: =shipping_compact!J$16 -> 0.04 | S50: =shipping_compact!L$16 -> 0 | T50: =shipping_compact!D$17 -> 6181584.9 | U50: =shipping_compact!E$17 -> 4380 | V50: =shipping_compact!F$17 -> 25 | W50: =shipping_compact!G$17 -> 1 | X50: =shipping_compact!I$17 -> 0 | Y50: =shipping_compact!J$17 -> 0.04 | Z50: =shipping_compact!L$17 -> 0.0002210194 | AA50: =shipping_compact!D$18 -> 1418767 | AB50: =shipping_compact!F$18 -> 30 | AC50: =shipping_compact!G$18 -> 0.996 | AD50: =shipping_compact!H$18 -> 0.685 | AE50: =shipping_compact!J$18 -> 0.043 | AF50: =shipping_compact!K$18 -> 0
A51: terminal_EU-PRT | B51: nh3 | C51: =_xlfn.CONCAT(B51,"_",A51) -> nh3_terminal_EU-PRT | D51: EU-PRT | E51: 37.961098 | F51: -8.8786877 | G51: Base | H51: =shipping_compact!D$12 -> 5986780 | I51: =shipping_compact!E$12 -> 6000 | J51: =shipping_compact!F$12 -> 30 | K51: =shipping_compact!G$12 -> 0.85 | L51: =shipping_compact!H$12 -> 0.992 | M51: =shipping_compact!J$12 -> 0.05 | N51: =shipping_compact!K$12 -> 0.2872 | O51: =shipping_compact!D$16 -> 293456.89 | P51: =shipping_compact!F$16 -> 30 | Q51: =shipping_compact!G$16 -> 1 | R51: =shipping_compact!J$16 -> 0.04 | S51: =shipping_compact!L$16 -> 0 | T51: =shipping_compact!D$17 -> 6181584.9 | U51: =shipping_compact!E$17 -> 4380 | V51: =shipping_compact!F$17 -> 25 | W51: =shipping_compact!G$17 -> 1 | X51: =shipping_compact!I$17 -> 0 | Y51: =shipping_compact!J$17 -> 0.04 | Z51: =shipping_compact!L$17 -> 0.0002210194 | AA51: =shipping_compact!D$18 -> 1418767 | AB51: =shipping_compact!F$18 -> 30 | AC51: =shipping_compact!G$18 -> 0.996 | AD51: =shipping_compact!H$18 -> 0.685 | AE51: =shipping_compact!J$18 -> 0.043 | AF51: =shipping_compact!K$18 -> 0
A52: terminal_EU-ESP | B52: nh3 | C52: =_xlfn.CONCAT(B52,"_",A52) -> nh3_terminal_EU-ESP | D52: EU-ESP | E52: 39.463713 | F52: -0.35881979 | G52: Base | H52: =shipping_compact!D$12 -> 5986780 | I52: =shipping_compact!E$12 -> 6000 | J52: =shipping_compact!F$12 -> 30 | K52: =shipping_compact!G$12 -> 0.85 | L52: =shipping_compact!H$12 -> 0.992 | M52: =shipping_compact!J$12 -> 0.05 | N52: =shipping_compact!K$12 -> 0.2872 | O52: =shipping_compact!D$16 -> 293456.89 | P52: =shipping_compact!F$16 -> 30 | Q52: =shipping_compact!G$16 -> 1 | R52: =shipping_compact!J$16 -> 0.04 | S52: =shipping_compact!L$16 -> 0 | T52: =shipping_compact!D$17 -> 6181584.9 | U52: =shipping_compact!E$17 -> 4380 | V52: =shipping_compact!F$17 -> 25 | W52: =shipping_compact!G$17 -> 1 | X52: =shipping_compact!I$17 -> 0 | Y52: =shipping_compact!J$17 -> 0.04 | Z52: =shipping_compact!L$17 -> 0.0002210194 | AA52: =shipping_compact!D$18 -> 1418767 | AB52: =shipping_compact!F$18 -> 30 | AC52: =shipping_compact!G$18 -> 0.996 | AD52: =shipping_compact!H$18 -> 0.685 | AE52: =shipping_compact!J$18 -> 0.043 | AF52: =shipping_compact!K$18 -> 0
A53: terminal_EU-ISL | B53: nh3 | C53: =_xlfn.CONCAT(B53,"_",A53) -> nh3_terminal_EU-ISL | D53: EU-ISL | E53: 64.094858 | F53: -21.853528 | G53: Base | H53: =shipping_compact!D$12 -> 5986780 | I53: =shipping_compact!E$12 -> 6000 | J53: =shipping_compact!F$12 -> 30 | K53: =shipping_compact!G$12 -> 0.85 | L53: =shipping_compact!H$12 -> 0.992 | M53: =shipping_compact!J$12 -> 0.05 | N53: =shipping_compact!K$12 -> 0.2872 | O53: =shipping_compact!D$16 -> 293456.89 | P53: =shipping_compact!F$16 -> 30 | Q53: =shipping_compact!G$16 -> 1 | R53: =shipping_compact!J$16 -> 0.04 | S53: =shipping_compact!L$16 -> 0 | T53: =shipping_compact!D$17 -> 6181584.9 | U53: =shipping_compact!E$17 -> 4380 | V53: =shipping_compact!F$17 -> 25 | W53: =shipping_compact!G$17 -> 1 | X53: =shipping_compact!I$17 -> 0 | Y53: =shipping_compact!J$17 -> 0.04 | Z53: =shipping_compact!L$17 -> 0.0002210194 | AA53: =shipping_compact!D$18 -> 1418767 | AB53: =shipping_compact!F$18 -> 30 | AC53: =shipping_compact!G$18 -> 0.996 | AD53: =shipping_compact!H$18 -> 0.685 | AE53: =shipping_compact!J$18 -> 0.043 | AF53: =shipping_compact!K$18 -> 0
A54: terminal_EU-ITA4 | B54: nh3 | C54: =_xlfn.CONCAT(B54,"_",A54) -> nh3_terminal_EU-ITA4 | D54: EU-ITA4 | E54: 45.205817 | F54: 12.293656 | G54: Base | H54: =shipping_compact!D$12 -> 5986780 | I54: =shipping_compact!E$12 -> 6000 | J54: =shipping_compact!F$12 -> 30 | K54: =shipping_compact!G$12 -> 0.85 | L54: =shipping_compact!H$12 -> 0.992 | M54: =shipping_compact!J$12 -> 0.05 | N54: =shipping_compact!K$12 -> 0.2872 | O54: =shipping_compact!D$16 -> 293456.89 | P54: =shipping_compact!F$16 -> 30 | Q54: =shipping_compact!G$16 -> 1 | R54: =shipping_compact!J$16 -> 0.04 | S54: =shipping_compact!L$16 -> 0 | T54: =shipping_compact!D$17 -> 6181584.9 | U54: =shipping_compact!E$17 -> 4380 | V54: =shipping_compact!F$17 -> 25 | W54: =shipping_compact!G$17 -> 1 | X54: =shipping_compact!I$17 -> 0 | Y54: =shipping_compact!J$17 -> 0.04 | Z54: =shipping_compact!L$17 -> 0.0002210194 | AA54: =shipping_compact!D$18 -> 1418767 | AB54: =shipping_compact!F$18 -> 30 | AC54: =shipping_compact!G$18 -> 0.996 | AD54: =shipping_compact!H$18 -> 0.685 | AE54: =shipping_compact!J$18 -> 0.043 | AF54: =shipping_compact!K$18 -> 0
A55: terminal_EU-ITA | B55: nh3 | C55: =_xlfn.CONCAT(B55,"_",A55) -> nh3_terminal_EU-ITA | D55: EU-ITA | E55: 45.205817 | F55: 12.293656 | G55: Base | H55: =shipping_compact!D$12 -> 5986780 | I55: =shipping_compact!E$12 -> 6000 | J55: =shipping_compact!F$12 -> 30 | K55: =shipping_compact!G$12 -> 0.85 | L55: =shipping_compact!H$12 -> 0.992 | M55: =shipping_compact!J$12 -> 0.05 | N55: =shipping_compact!K$12 -> 0.2872 | O55: =shipping_compact!D$16 -> 293456.89 | P55: =shipping_compact!F$16 -> 30 | Q55: =shipping_compact!G$16 -> 1 | R55: =shipping_compact!J$16 -> 0.04 | S55: =shipping_compact!L$16 -> 0 | T55: =shipping_compact!D$17 -> 6181584.9 | U55: =shipping_compact!E$17 -> 4380 | V55: =shipping_compact!F$17 -> 25 | W55: =shipping_compact!G$17 -> 1 | X55: =shipping_compact!I$17 -> 0 | Y55: =shipping_compact!J$17 -> 0.04 | Z55: =shipping_compact!L$17 -> 0.0002210194 | AA55: =shipping_compact!D$18 -> 1418767 | AB55: =shipping_compact!F$18 -> 30 | AC55: =shipping_compact!G$18 -> 0.996 | AD55: =shipping_compact!H$18 -> 0.685 | AE55: =shipping_compact!J$18 -> 0.043 | AF55: =shipping_compact!K$18 -> 0
A56: terminal_AS-TUR | B56: nh3 | C56: =_xlfn.CONCAT(B56,"_",A56) -> nh3_terminal_AS-TUR | D56: AS-TUR | E56: 36.825941 | F56: 36.177898 | G56: Base | H56: =shipping_compact!D$12 -> 5986780 | I56: =shipping_compact!E$12 -> 6000 | J56: =shipping_compact!F$12 -> 30 | K56: =shipping_compact!G$12 -> 0.85 | L56: =shipping_compact!H$12 -> 0.992 | M56: =shipping_compact!J$12 -> 0.05 | N56: =shipping_compact!K$12 -> 0.2872 | O56: =shipping_compact!D$16 -> 293456.89 | P56: =shipping_compact!F$16 -> 30 | Q56: =shipping_compact!G$16 -> 1 | R56: =shipping_compact!J$16 -> 0.04 | S56: =shipping_compact!L$16 -> 0 | T56: =shipping_compact!D$17 -> 6181584.9 | U56: =shipping_compact!E$17 -> 4380 | V56: =shipping_compact!F$17 -> 25 | W56: =shipping_compact!G$17 -> 1 | X56: =shipping_compact!I$17 -> 0 | Y56: =shipping_compact!J$17 -> 0.04 | Z56: =shipping_compact!L$17 -> 0.0002210194 | AA56: =shipping_compact!D$18 -> 1418767 | AB56: =shipping_compact!F$18 -> 30 | AC56: =shipping_compact!G$18 -> 0.996 | AD56: =shipping_compact!H$18 -> 0.685 | AE56: =shipping_compact!J$18 -> 0.043 | AF56: =shipping_compact!K$18 -> 0
A57: terminal_EU-SWE3 | B57: nh3 | C57: =_xlfn.CONCAT(B57,"_",A57) -> nh3_terminal_EU-SWE3 | D57: EU-SWE3 | E57: 58.913025 | F57: 17.96051 | G57: Base | H57: =shipping_compact!D$12 -> 5986780 | I57: =shipping_compact!E$12 -> 6000 | J57: =shipping_compact!F$12 -> 30 | K57: =shipping_compact!G$12 -> 0.85 | L57: =shipping_compact!H$12 -> 0.992 | M57: =shipping_compact!J$12 -> 0.05 | N57: =shipping_compact!K$12 -> 0.2872 | O57: =shipping_compact!D$16 -> 293456.89 | P57: =shipping_compact!F$16 -> 30 | Q57: =shipping_compact!G$16 -> 1 | R57: =shipping_compact!J$16 -> 0.04 | S57: =shipping_compact!L$16 -> 0 | T57: =shipping_compact!D$17 -> 6181584.9 | U57: =shipping_compact!E$17 -> 4380 | V57: =shipping_compact!F$17 -> 25 | W57: =shipping_compact!G$17 -> 1 | X57: =shipping_compact!I$17 -> 0 | Y57: =shipping_compact!J$17 -> 0.04 | Z57: =shipping_compact!L$17 -> 0.0002210194 | AA57: =shipping_compact!D$18 -> 1418767 | AB57: =shipping_compact!F$18 -> 30 | AC57: =shipping_compact!G$18 -> 0.996 | AD57: =shipping_compact!H$18 -> 0.685 | AE57: =shipping_compact!J$18 -> 0.043 | AF57: =shipping_compact!K$18 -> 0
A58: terminal_EU-SWE | B58: nh3 | C58: =_xlfn.CONCAT(B58,"_",A58) -> nh3_terminal_EU-SWE | D58: EU-SWE | E58: 58.913025 | F58: 17.96051 | G58: Base | H58: =shipping_compact!D$12 -> 5986780 | I58: =shipping_compact!E$12 -> 6000 | J58: =shipping_compact!F$12 -> 30 | K58: =shipping_compact!G$12 -> 0.85 | L58: =shipping_compact!H$12 -> 0.992 | M58: =shipping_compact!J$12 -> 0.05 | N58: =shipping_compact!K$12 -> 0.2872 | O58: =shipping_compact!D$16 -> 293456.89 | P58: =shipping_compact!F$16 -> 30 | Q58: =shipping_compact!G$16 -> 1 | R58: =shipping_compact!J$16 -> 0.04 | S58: =shipping_compact!L$16 -> 0 | T58: =shipping_compact!D$17 -> 6181584.9 | U58: =shipping_compact!E$17 -> 4380 | V58: =shipping_compact!F$17 -> 25 | W58: =shipping_compact!G$17 -> 1 | X58: =shipping_compact!I$17 -> 0 | Y58: =shipping_compact!J$17 -> 0.04 | Z58: =shipping_compact!L$17 -> 0.0002210194 | AA58: =shipping_compact!D$18 -> 1418767 | AB58: =shipping_compact!F$18 -> 30 | AC58: =shipping_compact!G$18 -> 0.996 | AD58: =shipping_compact!H$18 -> 0.685 | AE58: =shipping_compact!J$18 -> 0.043 | AF58: =shipping_compact!K$18 -> 0
A59: terminal_EU-GBR | B59: nh3 | C59: =_xlfn.CONCAT(B59,"_",A59) -> nh3_terminal_EU-GBR | D59: EU-GBR | E59: 51.70829 | F59: -5.0646298 | G59: Base | H59: =shipping_compact!D$12 -> 5986780 | I59: =shipping_compact!E$12 -> 6000 | J59: =shipping_compact!F$12 -> 30 | K59: =shipping_compact!G$12 -> 0.85 | L59: =shipping_compact!H$12 -> 0.992 | M59: =shipping_compact!J$12 -> 0.05 | N59: =shipping_compact!K$12 -> 0.2872 | O59: =shipping_compact!D$16 -> 293456.89 | P59: =shipping_compact!F$16 -> 30 | Q59: =shipping_compact!G$16 -> 1 | R59: =shipping_compact!J$16 -> 0.04 | S59: =shipping_compact!L$16 -> 0 | T59: =shipping_compact!D$17 -> 6181584.9 | U59: =shipping_compact!E$17 -> 4380 | V59: =shipping_compact!F$17 -> 25 | W59: =shipping_compact!G$17 -> 1 | X59: =shipping_compact!I$17 -> 0 | Y59: =shipping_compact!J$17 -> 0.04 | Z59: =shipping_compact!L$17 -> 0.0002210194 | AA59: =shipping_compact!D$18 -> 1418767 | AB59: =shipping_compact!F$18 -> 30 | AC59: =shipping_compact!G$18 -> 0.996 | AD59: =shipping_compact!H$18 -> 0.685 | AE59: =shipping_compact!J$18 -> 0.043 | AF59: =shipping_compact!K$18 -> 0
A60: terminal_AS-QAT | B60: nh3 | C60: =_xlfn.CONCAT(B60,"_",A60) -> nh3_terminal_AS-QAT | D60: AS-QAT | E60: 25.883521 | F60: 51.480261 | G60: Base | H60: =shipping_compact!D$12 -> 5986780 | I60: =shipping_compact!E$12 -> 6000 | J60: =shipping_compact!F$12 -> 30 | K60: =shipping_compact!G$12 -> 0.85 | L60: =shipping_compact!H$12 -> 0.992 | M60: =shipping_compact!J$12 -> 0.05 | N60: =shipping_compact!K$12 -> 0.2872 | O60: =shipping_compact!D$16 -> 293456.89 | P60: =shipping_compact!F$16 -> 30 | Q60: =shipping_compact!G$16 -> 1 | R60: =shipping_compact!J$16 -> 0.04 | S60: =shipping_compact!L$16 -> 0 | T60: =shipping_compact!D$17 -> 6181584.9 | U60: =shipping_compact!E$17 -> 4380 | V60: =shipping_compact!F$17 -> 25 | W60: =shipping_compact!G$17 -> 1 | X60: =shipping_compact!I$17 -> 0 | Y60: =shipping_compact!J$17 -> 0.04 | Z60: =shipping_compact!L$17 -> 0.0002210194 | AA60: =shipping_compact!D$18 -> 1418767 | AB60: =shipping_compact!F$18 -> 30 | AC60: =shipping_compact!G$18 -> 0.996 | AD60: =shipping_compact!H$18 -> 0.685 | AE60: =shipping_compact!J$18 -> 0.043 | AF60: =shipping_compact!K$18 -> 0
A61: terminal_AS-IND-WE | B61: nh3 | C61: =_xlfn.CONCAT(B61,"_",A61) -> nh3_terminal_AS-IND-WE | D61: AS-IND | E61: 18.944742 | F61: 72.950074 | G61: Base | H61: =shipping_compact!D$12 -> 5986780 | I61: =shipping_compact!E$12 -> 6000 | J61: =shipping_compact!F$12 -> 30 | K61: =shipping_compact!G$12 -> 0.85 | L61: =shipping_compact!H$12 -> 0.992 | M61: =shipping_compact!J$12 -> 0.05 | N61: =shipping_compact!K$12 -> 0.2872 | O61: =shipping_compact!D$16 -> 293456.89 | P61: =shipping_compact!F$16 -> 30 | Q61: =shipping_compact!G$16 -> 1 | R61: =shipping_compact!J$16 -> 0.04 | S61: =shipping_compact!L$16 -> 0 | T61: =shipping_compact!D$17 -> 6181584.9 | U61: =shipping_compact!E$17 -> 4380 | V61: =shipping_compact!F$17 -> 25 | W61: =shipping_compact!G$17 -> 1 | X61: =shipping_compact!I$17 -> 0 | Y61: =shipping_compact!J$17 -> 0.04 | Z61: =shipping_compact!L$17 -> 0.0002210194 | AA61: =shipping_compact!D$18 -> 1418767 | AB61: =shipping_compact!F$18 -> 30 | AC61: =shipping_compact!G$18 -> 0.996 | AD61: =shipping_compact!H$18 -> 0.685 | AE61: =shipping_compact!J$18 -> 0.043 | AF61: =shipping_compact!K$18 -> 0
... A97: terminal_AF-EGY | B97: nh3 | C97: =_xlfn.CONCAT(B97,"_",A97) -> nh3_terminal_AF-EGY | D97: AF-EGY | E97: 29.916289 | F97: 32.449177 | G97: Base | H97: =shipping_compact!D$12 -> 5986780 | I97: =shipping_compact!E$12 -> 6000 | J97: =shipping_compact!F$12 -> 30 | K97: =shipping_compact!G$12 -> 0.85 | L97: =shipping_compact!H$12 -> 0.992 | M97: =shipping_compact!J$12 -> 0.05 | N97: =shipping_compact!K$12 -> 0.2872 | O97: =shipping_compact!D$16 -> 293456.89 | P97: =shipping_compact!F$16 -> 30 | Q97: =shipping_compact!G$16 -> 1 | R97: =shipping_compact!J$16 -> 0.04 | S97: =shipping_compact!L$16 -> 0 | T97: =shipping_compact!D$17 -> 6181584.9 | U97: =shipping_compact!E$17 -> 4380 | V97: =shipping_compact!F$17 -> 25 | W97: =shipping_compact!G$17 -> 1 | X97: =shipping_compact!I$17 -> 0 | Y97: =shipping_compact!J$17 -> 0.04 | Z97: =shipping_compact!L$17 -> 0.0002210194 | AA97: =shipping_compact!D$18 -> 1418767 | AB97: =shipping_compact!F$18 -> 30 | AC97: =shipping_compact!G$18 -> 0.996 | AD97: =shipping_compact!H$18 -> 0.685 | AE97: =shipping_compact!J$18 -> 0.043 | AF97: =shipping_compact!K$18 -> 0
A98: terminal_EU-NLD | B98: ch3oh | C98: =_xlfn.CONCAT(B98,"_",A98) -> ch3oh_terminal_EU-NLD | D98: EU-NLD | E98: 51.948455 | F98: 4.140296 | G98: Base | H98: =shipping_compact!D$21 -> 7300000 | I98: =shipping_compact!E$21 -> 6000 | J98: =shipping_compact!F$21 -> 30 | K98: =shipping_compact!G$21 -> 0.5925 | L98: =shipping_compact!H$21 -> 1 | M98: =shipping_compact!J$21 -> 0.04 | N98: =shipping_compact!K$21 -> 0 | O98: =shipping_compact!D$25 -> 293456.89 | P98: =shipping_compact!F$25 -> 30 | Q98: =shipping_compact!G$25 -> 1 | R98: =shipping_compact!J$25 -> 0.04 | S98: =shipping_compact!L$25 -> 0 | T98: =shipping_compact!D$26 -> 1756697 | U98: =shipping_compact!E$26 -> 4380 | V98: =shipping_compact!F$26 -> 25 | W98: =shipping_compact!G$26 -> 1 | X98: =shipping_compact!I$26 -> 0 | Y98: =shipping_compact!J$26 -> 0.04 | Z98: =shipping_compact!L$26 -> 0.00018083405 | AA98: =shipping_compact!D$27 -> 22653 | AB98: =shipping_compact!F$27 -> 30 | AC98: =shipping_compact!G$27 -> 0.99 | AD98: =shipping_compact!H$27 -> 0.833 | AE98: =shipping_compact!J$27 -> 0.04 | AF98: =shipping_compact!K$27 -> 0
A99: terminal_EU-PRT | B99: ch3oh | C99: =_xlfn.CONCAT(B99,"_",A99) -> ch3oh_terminal_EU-PRT | D99: EU-PRT | E99: 37.961098 | F99: -8.8786877 | G99: Base | H99: =shipping_compact!D$21 -> 7300000 | I99: =shipping_compact!E$21 -> 6000 | J99: =shipping_compact!F$21 -> 30 | K99: =shipping_compact!G$21 -> 0.5925 | L99: =shipping_compact!H$21 -> 1 | M99: =shipping_compact!J$21 -> 0.04 | N99: =shipping_compact!K$21 -> 0 | O99: =shipping_compact!D$25 -> 293456.89 | P99: =shipping_compact!F$25 -> 30 | Q99: =shipping_compact!G$25 -> 1 | R99: =shipping_compact!J$25 -> 0.04 | S99: =shipping_compact!L$25 -> 0 | T99: =shipping_compact!D$26 -> 1756697 | U99: =shipping_compact!E$26 -> 4380 | V99: =shipping_compact!F$26 -> 25 | W99: =shipping_compact!G$26 -> 1 | X99: =shipping_compact!I$26 -> 0 | Y99: =shipping_compact!J$26 -> 0.04 | Z99: =shipping_compact!L$26 -> 0.00018083405 | AA99: =shipping_compact!D$27 -> 22653 | AB99: =shipping_compact!F$27 -> 30 | AC99: =shipping_compact!G$27 -> 0.99 | AD99: =shipping_compact!H$27 -> 0.833 | AE99: =shipping_compact!J$27 -> 0.04 | AF99: =shipping_compact!K$27 -> 0
A100: terminal_EU-ESP | B100: ch3oh | C100: =_xlfn.CONCAT(B100,"_",A100) -> ch3oh_terminal_EU-ESP | D100: EU-ESP | E100: 39.463713 | F100: -0.35881979 | G100: Base | H100: =shipping_compact!D$21 -> 7300000 | I100: =shipping_compact!E$21 -> 6000 | J100: =shipping_compact!F$21 -> 30 | K100: =shipping_compact!G$21 -> 0.5925 | L100: =shipping_compact!H$21 -> 1 | M100: =shipping_compact!J$21 -> 0.04 | N100: =shipping_compact!K$21 -> 0 | O100: =shipping_compact!D$25 -> 293456.89 | P100: =shipping_compact!F$25 -> 30 | Q100: =shipping_compact!G$25 -> 1 | R100: =shipping_compact!J$25 -> 0.04 | S100: =shipping_compact!L$25 -> 0 | T100: =shipping_compact!D$26 -> 1756697 | U100: =shipping_compact!E$26 -> 4380 | V100: =shipping_compact!F$26 -> 25 | W100: =shipping_compact!G$26 -> 1 | X100: =shipping_compact!I$26 -> 0 | Y100: =shipping_compact!J$26 -> 0.04 | Z100: =shipping_compact!L$26 -> 0.00018083405 | AA100: =shipping_compact!D$27 -> 22653 | AB100: =shipping_compact!F$27 -> 30 | AC100: =shipping_compact!G$27 -> 0.99 | AD100: =shipping_compact!H$27 -> 0.833 | AE100: =shipping_compact!J$27 -> 0.04 | AF100: =shipping_compact!K$27 -> 0
A101: terminal_EU-ISL | B101: ch3oh | C101: =_xlfn.CONCAT(B101,"_",A101) -> ch3oh_terminal_EU-ISL | D101: EU-ISL | E101: 64.094858 | F101: -21.853528 | G101: Base | H101: =shipping_compact!D$21 -> 7300000 | I101: =shipping_compact!E$21 -> 6000 | J101: =shipping_compact!F$21 -> 30 | K101: =shipping_compact!G$21 -> 0.5925 | L101: =shipping_compact!H$21 -> 1 | M101: =shipping_compact!J$21 -> 0.04 | N101: =shipping_compact!K$21 -> 0 | O101: =shipping_compact!D$25 -> 293456.89 | P101: =shipping_compact!F$25 -> 30 | Q101: =shipping_compact!G$25 -> 1 | R101: =shipping_compact!J$25 -> 0.04 | S101: =shipping_compact!L$25 -> 0 | T101: =shipping_compact!D$26 -> 1756697 | U101: =shipping_compact!E$26 -> 4380 | V101: =shipping_compact!F$26 -> 25 | W101: =shipping_compact!G$26 -> 1 | X101: =shipping_compact!I$26 -> 0 | Y101: =shipping_compact!J$26 -> 0.04 | Z101: =shipping_compact!L$26 -> 0.00018083405 | AA101: =shipping_compact!D$27 -> 22653 | AB101: =shipping_compact!F$27 -> 30 | AC101: =shipping_compact!G$27 -> 0.99 | AD101: =shipping_compact!H$27 -> 0.833 | AE101: =shipping_compact!J$27 -> 0.04 | AF101: =shipping_compact!K$27 -> 0
A102: terminal_EU-ITA4 | B102: ch3oh | C102: =_xlfn.CONCAT(B102,"_",A102) -> ch3oh_terminal_EU-ITA4 | D102: EU-ITA4 | E102: 45.205817 | F102: 12.293656 | G102: Base | H102: =shipping_compact!D$21 -> 7300000 | I102: =shipping_compact!E$21 -> 6000 | J102: =shipping_compact!F$21 -> 30 | K102: =shipping_compact!G$21 -> 0.5925 | L102: =shipping_compact!H$21 -> 1 | M102: =shipping_compact!J$21 -> 0.04 | N102: =shipping_compact!K$21 -> 0 | O102: =shipping_compact!D$25 -> 293456.89 | P102: =shipping_compact!F$25 -> 30 | Q102: =shipping_compact!G$25 -> 1 | R102: =shipping_compact!J$25 -> 0.04 | S102: =shipping_compact!L$25 -> 0 | T102: =shipping_compact!D$26 -> 1756697 | U102: =shipping_compact!E$26 -> 4380 | V102: =shipping_compact!F$26 -> 25 | W102: =shipping_compact!G$26 -> 1 | X102: =shipping_compact!I$26 -> 0 | Y102: =shipping_compact!J$26 -> 0.04 | Z102: =shipping_compact!L$26 -> 0.00018083405 | AA102: =shipping_compact!D$27 -> 22653 | AB102: =shipping_compact!F$27 -> 30 | AC102: =shipping_compact!G$27 -> 0.99 | AD102: =shipping_compact!H$27 -> 0.833 | AE102: =shipping_compact!J$27 -> 0.04 | AF102: =shipping_compact!K$27 -> 0
A103: terminal_EU-ITA | B103: ch3oh | C103: =_xlfn.CONCAT(B103,"_",A103) -> ch3oh_terminal_EU-ITA | D103: EU-ITA | E103: 45.205817 | F103: 12.293656 | G103: Base | H103: =shipping_compact!D$21 -> 7300000 | I103: =shipping_compact!E$21 -> 6000 | J103: =shipping_compact!F$21 -> 30 | K103: =shipping_compact!G$21 -> 0.5925 | L103: =shipping_compact!H$21 -> 1 | M103: =shipping_compact!J$21 -> 0.04 | N103: =shipping_compact!K$21 -> 0 | O103: =shipping_compact!D$25 -> 293456.89 | P103: =shipping_compact!F$25 -> 30 | Q103: =shipping_compact!G$25 -> 1 | R103: =shipping_compact!J$25 -> 0.04 | S103: =shipping_compact!L$25 -> 0 | T103: =shipping_compact!D$26 -> 1756697 | U103: =shipping_compact!E$26 -> 4380 | V103: =shipping_compact!F$26 -> 25 | W103: =shipping_compact!G$26 -> 1 | X103: =shipping_compact!I$26 -> 0 | Y103: =shipping_compact!J$26 -> 0.04 | Z103: =shipping_compact!L$26 -> 0.00018083405 | AA103: =shipping_compact!D$27 -> 22653 | AB103: =shipping_compact!F$27 -> 30 | AC103: =shipping_compact!G$27 -> 0.99 | AD103: =shipping_compact!H$27 -> 0.833 | AE103: =shipping_compact!J$27 -> 0.04 | AF103: =shipping_compact!K$27 -> 0
A104: terminal_AS-TUR | B104: ch3oh | C104: =_xlfn.CONCAT(B104,"_",A104) -> ch3oh_terminal_AS-TUR | D104: AS-TUR | E104: 36.825941 | F104: 36.177898 | G104: Base | H104: =shipping_compact!D$21 -> 7300000 | I104: =shipping_compact!E$21 -> 6000 | J104: =shipping_compact!F$21 -> 30 | K104: =shipping_compact!G$21 -> 0.5925 | L104: =shipping_compact!H$21 -> 1 | M104: =shipping_compact!J$21 -> 0.04 | N104: =shipping_compact!K$21 -> 0 | O104: =shipping_compact!D$25 -> 293456.89 | P104: =shipping_compact!F$25 -> 30 | Q104: =shipping_compact!G$25 -> 1 | R104: =shipping_compact!J$25 -> 0.04 | S104: =shipping_compact!L$25 -> 0 | T104: =shipping_compact!D$26 -> 1756697 | U104: =shipping_compact!E$26 -> 4380 | V104: =shipping_compact!F$26 -> 25 | W104: =shipping_compact!G$26 -> 1 | X104: =shipping_compact!I$26 -> 0 | Y104: =shipping_compact!J$26 -> 0.04 | Z104: =shipping_compact!L$26 -> 0.00018083405 | AA104: =shipping_compact!D$27 -> 22653 | AB104: =shipping_compact!F$27 -> 30 | AC104: =shipping_compact!G$27 -> 0.99 | AD104: =shipping_compact!H$27 -> 0.833 | AE104: =shipping_compact!J$27 -> 0.04 | AF104: =shipping_compact!K$27 -> 0
A105: terminal_EU-SWE3 | B105: ch3oh | C105: =_xlfn.CONCAT(B105,"_",A105) -> ch3oh_terminal_EU-SWE3 | D105: EU-SWE3 | E105: 58.913025 | F105: 17.96051 | G105: Base | H105: =shipping_compact!D$21 -> 7300000 | I105: =shipping_compact!E$21 -> 6000 | J105: =shipping_compact!F$21 -> 30 | K105: =shipping_compact!G$21 -> 0.5925 | L105: =shipping_compact!H$21 -> 1 | M105: =shipping_compact!J$21 -> 0.04 | N105: =shipping_compact!K$21 -> 0 | O105: =shipping_compact!D$25 -> 293456.89 | P105: =shipping_compact!F$25 -> 30 | Q105: =shipping_compact!G$25 -> 1 | R105: =shipping_compact!J$25 -> 0.04 | S105: =shipping_compact!L$25 -> 0 | T105: =shipping_compact!D$26 -> 1756697 | U105: =shipping_compact!E$26 -> 4380 | V105: =shipping_compact!F$26 -> 25 | W105: =shipping_compact!G$26 -> 1 | X105: =shipping_compact!I$26 -> 0 | Y105: =shipping_compact!J$26 -> 0.04 | Z105: =shipping_compact!L$26 -> 0.00018083405 | AA105: =shipping_compact!D$27 -> 22653 | AB105: =shipping_compact!F$27 -> 30 | AC105: =shipping_compact!G$27 -> 0.99 | AD105: =shipping_compact!H$27 -> 0.833 | AE105: =shipping_compact!J$27 -> 0.04 | AF105: =shipping_compact!K$27 -> 0
A106: terminal_EU-SWE | B106: ch3oh | C106: =_xlfn.CONCAT(B106,"_",A106) -> ch3oh_terminal_EU-SWE | D106: EU-SWE | E106: 58.913025 | F106: 17.96051 | G106: Base | H106: =shipping_compact!D$21 -> 7300000 | I106: =shipping_compact!E$21 -> 6000 | J106: =shipping_compact!F$21 -> 30 | K106: =shipping_compact!G$21 -> 0.5925 | L106: =shipping_compact!H$21 -> 1 | M106: =shipping_compact!J$21 -> 0.04 | N106: =shipping_compact!K$21 -> 0 | O106: =shipping_compact!D$25 -> 293456.89 | P106: =shipping_compact!F$25 -> 30 | Q106: =shipping_compact!G$25 -> 1 | R106: =shipping_compact!J$25 -> 0.04 | S106: =shipping_compact!L$25 -> 0 | T106: =shipping_compact!D$26 -> 1756697 | U106: =shipping_compact!E$26 -> 4380 | V106: =shipping_compact!F$26 -> 25 | W106: =shipping_compact!G$26 -> 1 | X106: =shipping_compact!I$26 -> 0 | Y106: =shipping_compact!J$26 -> 0.04 | Z106: =shipping_compact!L$26 -> 0.00018083405 | AA106: =shipping_compact!D$27 -> 22653 | AB106: =shipping_compact!F$27 -> 30 | AC106: =shipping_compact!G$27 -> 0.99 | AD106: =shipping_compact!H$27 -> 0.833 | AE106: =shipping_compact!J$27 -> 0.04 | AF106: =shipping_compact!K$27 -> 0
A107: terminal_EU-GBR | B107: ch3oh | C107: =_xlfn.CONCAT(B107,"_",A107) -> ch3oh_terminal_EU-GBR | D107: EU-GBR | E107: 51.70829 | F107: -5.0646298 | G107: Base | H107: =shipping_compact!D$21 -> 7300000 | I107: =shipping_compact!E$21 -> 6000 | J107: =shipping_compact!F$21 -> 30 | K107: =shipping_compact!G$21 -> 0.5925 | L107: =shipping_compact!H$21 -> 1 | M107: =shipping_compact!J$21 -> 0.04 | N107: =shipping_compact!K$21 -> 0 | O107: =shipping_compact!D$25 -> 293456.89 | P107: =shipping_compact!F$25 -> 30 | Q107: =shipping_compact!G$25 -> 1 | R107: =shipping_compact!J$25 -> 0.04 | S107: =shipping_compact!L$25 -> 0 | T107: =shipping_compact!D$26 -> 1756697 | U107: =shipping_compact!E$26 -> 4380 | V107: =shipping_compact!F$26 -> 25 | W107: =shipping_compact!G$26 -> 1 | X107: =shipping_compact!I$26 -> 0 | Y107: =shipping_compact!J$26 -> 0.04 | Z107: =shipping_compact!L$26 -> 0.00018083405 | AA107: =shipping_compact!D$27 -> 22653 | AB107: =shipping_compact!F$27 -> 30 | AC107: =shipping_compact!G$27 -> 0.99 | AD107: =shipping_compact!H$27 -> 0.833 | AE107: =shipping_compact!J$27 -> 0.04 | AF107: =shipping_compact!K$27 -> 0
A108: terminal_AS-QAT | B108: ch3oh | C108: =_xlfn.CONCAT(B108,"_",A108) -> ch3oh_terminal_AS-QAT | D108: AS-QAT | E108: 25.883521 | F108: 51.480261 | G108: Base | H108: =shipping_compact!D$21 -> 7300000 | I108: =shipping_compact!E$21 -> 6000 | J108: =shipping_compact!F$21 -> 30 | K108: =shipping_compact!G$21 -> 0.5925 | L108: =shipping_compact!H$21 -> 1 | M108: =shipping_compact!J$21 -> 0.04 | N108: =shipping_compact!K$21 -> 0 | O108: =shipping_compact!D$25 -> 293456.89 | P108: =shipping_compact!F$25 -> 30 | Q108: =shipping_compact!G$25 -> 1 | R108: =shipping_compact!J$25 -> 0.04 | S108: =shipping_compact!L$25 -> 0 | T108: =shipping_compact!D$26 -> 1756697 | U108: =shipping_compact!E$26 -> 4380 | V108: =shipping_compact!F$26 -> 25 | W108: =shipping_compact!G$26 -> 1 | X108: =shipping_compact!I$26 -> 0 | Y108: =shipping_compact!J$26 -> 0.04 | Z108: =shipping_compact!L$26 -> 0.00018083405 | AA108: =shipping_compact!D$27 -> 22653 | AB108: =shipping_compact!F$27 -> 30 | AC108: =shipping_compact!G$27 -> 0.99 | AD108: =shipping_compact!H$27 -> 0.833 | AE108: =shipping_compact!J$27 -> 0.04 | AF108: =shipping_compact!K$27 -> 0
A109: terminal_AS-IND-WE | B109: ch3oh | C109: =_xlfn.CONCAT(B109,"_",A109) -> ch3oh_terminal_AS-IND-WE | D109: AS-IND | E109: 18.944742 | F109: 72.950074 | G109: Base | H109: =shipping_compact!D$21 -> 7300000 | I109: =shipping_compact!E$21 -> 6000 | J109: =shipping_compact!F$21 -> 30 | K109: =shipping_compact!G$21 -> 0.5925 | L109: =shipping_compact!H$21 -> 1 | M109: =shipping_compact!J$21 -> 0.04 | N109: =shipping_compact!K$21 -> 0 | O109: =shipping_compact!D$25 -> 293456.89 | P109: =shipping_compact!F$25 -> 30 | Q109: =shipping_compact!G$25 -> 1 | R109: =shipping_compact!J$25 -> 0.04 | S109: =shipping_compact!L$25 -> 0 | T109: =shipping_compact!D$26 -> 1756697 | U109: =shipping_compact!E$26 -> 4380 | V109: =shipping_compact!F$26 -> 25 | W109: =shipping_compact!G$26 -> 1 | X109: =shipping_compact!I$26 -> 0 | Y109: =shipping_compact!J$26 -> 0.04 | Z109: =shipping_compact!L$26 -> 0.00018083405 | AA109: =shipping_compact!D$27 -> 22653 | AB109: =shipping_compact!F$27 -> 30 | AC109: =shipping_compact!G$27 -> 0.99 | AD109: =shipping_compact!H$27 -> 0.833 | AE109: =shipping_compact!J$27 -> 0.04 | AF109: =shipping_compact!K$27 -> 0
... A145: terminal_AF-EGY | B145: ch3oh | C145: =_xlfn.CONCAT(B145,"_",A145) -> ch3oh_terminal_AF-EGY | D145: AF-EGY | E145: 29.916289 | F145: 32.449177 | G145: Base | H145: =shipping_compact!D$21 -> 7300000 | I145: =shipping_compact!E$21 -> 6000 | J145: =shipping_compact!F$21 -> 30 | K145: =shipping_compact!G$21 -> 0.5925 | L145: =shipping_compact!H$21 -> 1 | M145: =shipping_compact!J$21 -> 0.04 | N145: =shipping_compact!K$21 -> 0 | O145: =shipping_compact!D$25 -> 293456.89 | P145: =shipping_compact!F$25 -> 30 | Q145: =shipping_compact!G$25 -> 1 | R145: =shipping_compact!J$25 -> 0.04 | S145: =shipping_compact!L$25 -> 0 | T145: =shipping_compact!D$26 -> 1756697 | U145: =shipping_compact!E$26 -> 4380 | V145: =shipping_compact!F$26 -> 25 | W145: =shipping_compact!G$26 -> 1 | X145: =shipping_compact!I$26 -> 0 | Y145: =shipping_compact!J$26 -> 0.04 | Z145: =shipping_compact!L$26 -> 0.00018083405 | AA145: =shipping_compact!D$27 -> 22653 | AB145: =shipping_compact!F$27 -> 30 | AC145: =shipping_compact!G$27 -> 0.99 | AD145: =shipping_compact!H$27 -> 0.833 | AE145: =shipping_compact!J$27 -> 0.04 | AF145: =shipping_compact!K$27 -> 0
